Workbook

Sheet BASE
A1: N° Vacante | B1: Fecha de solicitud | C1: Días de apertura | D1: Selector | E1: Estado de aprobación | F1: ¿Aplica para movimiento interno de reasignación? | G1: Confidencial | H1: Vacante sujeta a futura desvinculación | I1: Fecha estimada de desvinculación | J1: Unidad de Negocio | K1: Razon Social | L1: Sector | M1: Centro de Costo | N1: Familia de Puesto | O1: Puesto | P1: Líder | Q1: Hiring Manager | R1: Status general | S1: Status del proceso | T1: Fecha estimada de ingreso | U1: Dificultad | V1: Prioridad | W1: Tipo de vacante | X1: Número de Legajo del reemplazo | Y1: Nombre de reemplazo | Z1: Motivo de contratación | AA1: Modalidad de contratación | AB1: Justificación de la cobertura | AC1: ¿Qué ocurre si la vacante no se cubre? | AD1: Horario | AE1: Lugar de trabajo | AF1: Fecha de cierre | AG1: Fecha de Ingreso | AH1: Tipo de Búsqueda | AI1: Fuente de selección | AJ1: Nombre del seleccionado/a | AK1: Remuneración acordada | AL1: CCT | AM1: Notebook | AN1: Blue | AO1: Comentarios
A2: 00001 | B2: 45673 | C2: =IF(B2="","",IF(OR(TRIM(R2)="En curso",TRIM(R2)="En proceso de ingreso"),TODAY()-B2,"Cerrada")) -> Cerrada | D2: Franco | E2: Aprobada | G2: No | J2: PREPAGA | K2: Cobensil SA | L2: Ventas Retail | M2: Comercial | N2: Comercial, ventas y cobranzas | O2: VENDEDOR/A | P2: Serafin | R2: Cerrada | S2: Ingreso | W2: Reemplazo | Y2: MOYANO ARIANA SOLEDAD (168710) | AA2: Inderminado | AD2: Lunes a Viernes de 10 a 18hs | AE2: Sede Colegiales (Lacroze 3257) | AF2: 46057 | AG2: 46063 | AJ2: BANEGAS NEMBHARD, MARYANA ALEXANDRA | AK2: $1.271.329,36 bruto / $1.036.688,00 neto | AL2: 130/75 | AM2: No | AN2: No
A3: 00002 | B3: 45678 | C3: =IF(B3="","",IF(OR(TRIM(R3)="En curso",TRIM(R3)="En proceso de ingreso"),TODAY()-B3,"Cerrada")) -> Cerrada | D3: Franco | E3: Aprobada | J3: PREPAGA | L3: Ventas Retail | M3: Comercial | N3: Comercial, ventas y cobranzas | O3: VENDEDOR/A | P3: Serafin | R3: Cerrada | S3: Ingreso | W3: Apertura de puesto | AA3: Inderminado | AF3: 46064 | AG3: 46071 | AJ3: Matias Yanez
A4: 00003 | B4: 45678 | C4: =IF(B4="","",IF(OR(TRIM(R4)="En curso",TRIM(R4)="En proceso de ingreso"),TODAY()-B4,"Cerrada")) -> Cerrada | D4: Franco | E4: Aprobada | J4: PREPAGA | L4: Ventas Retail | M4: Comercial | N4: Comercial, ventas y cobranzas | O4: VENDEDOR/A | P4: Serafin | R4: Cerrada | S4: Ingreso | W4: Apertura de puesto | AA4: Inderminado | AF4: 46064 | AG4: 46071 | AJ4: Perla Carvajal
A5: 00004 | B5: 45678 | C5: =IF(B5="","",IF(OR(TRIM(R5)="En curso",TRIM(R5)="En proceso de ingreso"),TODAY()-B5,"Cerrada")) -> Cerrada | D5: Franco | E5: Aprobada | G5: No | J5: PREPAGA | K5: Cobensil SA | L5: Ventas Retail | M5: Comercial | N5: Comercial, ventas y cobranzas | O5: VENDEDOR/A | P5: Serafin | Q5: Sergio Couceiro | R5: Cerrada | S5: Ingreso | T5: 46100 | U5: Baja | V5: Media | W5: Apertura de puesto | AA5: Inderminado | AD5: Lunes a Viernes de 10 a 18 hs | AE5: Cober - Vicente Lopez | AF5: 46094 | AG5: 46100 | AH5: Externa | AI5: Consultora | AJ5: Lady Gomes | AK5: $1.271.329,36 Bruto | AL5: 130/75 | AM5: NO | AN5: No
A6: 00005 | B6: 45678 | C6: =IF(B6="","",IF(OR(TRIM(R6)="En curso",TRIM(R6)="En proceso de ingreso"),TODAY()-B6,"Cerrada")) -> Cerrada | D6: Franco | E6: Aprobada | G6: No | J6: PREPAGA | K6: Cobensil SA | L6: Ventas Retail | M6: Comercial | N6: Comercial, ventas y cobranzas | O6: VENDEDOR/A | P6: Serafin | Q6: Sergio Couceiro | R6: Cerrada | S6: Ingreso | T6: 46100 | U6: Baja | V6: Media | W6: Apertura de puesto | AA6: Inderminado | AD6: Lunes a Viernes de 10 a 18 hs | AE6: Cober - Vicente Lopez | AF6: 46094 | AG6: 46100 | AH6: Externa | AI6: Consultora | AJ6: Joel Dree | AK6: $1.271.329,36 Bruto | AL6: 130/75 | AM6: NO | AN6: No
A7: 00006 | B7: 45678 | C7: =IF(B7="","",IF(OR(TRIM(R7)="En curso",TRIM(R7)="En proceso de ingreso"),TODAY()-B7,"Cerrada")) -> Cerrada | D7: Franco | E7: Aprobada | G7: No | J7: PREPAGA | K7: Cobensil SA | L7: Ventas Retail | M7: Comercial | N7: Comercial, ventas y cobranzas | O7: VENDEDOR/A | P7: Serafin | Q7: Sergio Couceiro | R7: Cerrada | S7: Ingreso | T7: 46100 | U7: Baja | V7: Media | W7: Apertura de puesto | AA7: Inderminado | AD7: Lunes a Viernes de 10 a 18 hs | AE7: Cober - Vicente Lopez | AF7: 46094 | AG7: 46100 | AH7: Externa | AI7: Consultora | AJ7: Romina Rojas | AK7: $1.271.329,36 Bruto | AL7: 130/75 | AM7: NO | AN7: No
A8: 00007 | B8: 45678 | C8: =IF(B8="","",IF(OR(TRIM(R8)="En curso",TRIM(R8)="En proceso de ingreso"),TODAY()-B8,"Cerrada")) -> Cerrada | D8: Franco | E8: Aprobada | G8: No | J8: PREPAGA | K8: Cobensil SA | L8: Ventas Retail | M8: Comercial | N8: Comercial, ventas y cobranzas | O8: VENDEDOR/A | P8: Serafin | Q8: Patricia Mozota | R8: Cerrada | S8: Ingreso | T8: 46100 | U8: Baja | V8: Media | W8: Apertura de puesto | AA8: Inderminado | AD8: Lunes a Viernes de 10 a 18 hs | AE8: Cober - Lacroze | AF8: 46094 | AG8: 46100 | AH8: Externa | AI8: Consultora | AJ8: Carolina Ledesma | AK8: $1.271.329,36 Bruto | AL8: 130/75 | AM8: NO | AN8: No
A9: 00008 | B9: 45678 | C9: =IF(B9="","",IF(OR(TRIM(R9)="En curso",TRIM(R9)="En proceso de ingreso"),TODAY()-B9,"Cerrada")) -> Cerrada | D9: Franco | E9: Aprobada | G9: No | J9: PREPAGA | K9: Cobensil SA | L9: Ventas Retail | M9: Comercial | N9: Comercial, ventas y cobranzas | O9: VENDEDOR/A | P9: Serafin | Q9: Patricia Mozota | R9: Cerrada | S9: Ingreso | T9: 46100 | U9: Baja | W9: Apertura de puesto | AA9: Inderminado | AD9: Lunes a Viernes de 10 a 18 hs | AE9: Cober - Lacroze | AF9: 46094 | AG9: 46100 | AH9: Externa | AI9: Consultora | AJ9: Julieta Gutcovsky | AK9: $1.271.329,36 Bruto | AL9: 130/75 | AM9: NO | AN9: No
A10: 00009 | B10: 45678 | C10: =IF(B10="","",IF(OR(TRIM(R10)="En curso",TRIM(R10)="En proceso de ingreso"),TODAY()-B10,"Cerrada")) -> Cerrada | D10: Franco | E10: Aprobada | G10: No | J10: PREPAGA | K10: Cobensil SA | L10: Ventas Retail | M10: Comercial | N10: Comercial, ventas y cobranzas | O10: VENDEDOR/A | P10: Serafin | Q10: Patricia Mozota | R10: Cerrada | S10: Ingreso | T10: 46100 | U10: Baja | W10: Apertura de puesto | AA10: Inderminado | AD10: Lunes a Viernes de 10 a 18 hs | AE10: Cober - Lacroze | AF10: 46094 | AG10: 46100 | AH10: Externa | AI10: Consultora | AJ10: Noelia Quintana | AK10: $1.271.329,36 Bruto | AL10: 130/75 | AM10: NO | AN10: No
A11: 00010 | B11: 45678 | C11: =IF(B11="","",IF(OR(TRIM(R11)="En curso",TRIM(R11)="En proceso de ingreso"),TODAY()-B11,"Cerrada")) -> Cerrada | D11: Franco | E11: Aprobada | J11: PREPAGA | K11: Bristol Medicine SRL | L11: Ventas Retail | M11: Comercial | N11: Comercial, ventas y cobranzas | O11: VENDEDOR/A | P11: Serafin | Q11: Gabriela Mira | R11: Cerrada | S11: Ingreso | T11: 46100 | U11: Baja | W11: Apertura de puesto | AA11: Inderminado | AD11: Lunes a Viernes de 10 a 17hs | AE11: Bristol - Céspedes | AF11: 46097 | AG11: 46100 | AH11: Externa | AI11: Consultora | AJ11: Ryan Hutchinson | AK11: $961.576,34 Bruto | AL11: 108/75 | AM11: NO | AN11: No
A12: 00011 | B12: 45678 | C12: =IF(B12="","",IF(OR(TRIM(R12)="En curso",TRIM(R12)="En proceso de ingreso"),TODAY()-B12,"Cerrada")) -> Cerrada | D12: Franco | E12: Aprobada | J12: PREPAGA | K12: Bristol Medicine SRL | L12: Ventas Retail | M12: Comercial | N12: Comercial, ventas y cobranzas | O12: VENDEDOR/A | P12: Serafin | Q12: Gabriela Mira | R12: Cerrada | S12: Ingreso | T12: 46100 | U12: Baja | W12: Apertura de puesto | AA12: Inderminado | AD12: Lunes a Viernes de 10 a 17hs | AE12: Bristol - Céspedes | AF12: 46097 | AG12: 46100 | AH12: Externa | AI12: Consultora | AJ12: Katia Lambare | AK12: $961.576,34 Bruto | AL12: 108/75 | AM12: NO | AN12: No
A13: 00012 | B13: 45678 | C13: =IF(B13="","",IF(OR(TRIM(R13)="En curso",TRIM(R13)="En proceso de ingreso"),TODAY()-B13,"Cerrada")) -> Cerrada | D13: Franco | E13: Aprobada | J13: PREPAGA | K13: Bristol Medicine SRL | L13: Ventas Retail | M13: Comercial | N13: Comercial, ventas y cobranzas | O13: VENDEDOR/A | P13: Serafin | Q13: Vanesa Serafin | R13: Cerrada | S13: Ingreso | T13: 46100 | U13: Baja | W13: Apertura de puesto | AA13: Inderminado | AD13: Lunes a Viernes de 10 a 17hs | AE13: Bristol - Céspedes | AF13: 46097 | AG13: 46100 | AH13: Externa | AI13: Consultora | AJ13: Brian Gryncwejg | AK13: $961.576,34 Bruto | AL13: 108/75 | AM13: NO | AN13: No
A14: 00013 | B14: 45818 | C14: =IF(B14="","",IF(OR(TRIM(R14)="En curso",TRIM(R14)="En proceso de ingreso"),TODAY()-B14,"Cerrada")) -> Cerrada | D14: Jose | E14: Aprobada | J14: DROGUERÍA | K14: Reinsal | L14: Ventas | M14: Comercial | N14: Liderazgo | O14: Jefe de Ventas | P14: Serpone | R14: Cerrada | S14: Ingreso | W14: Reemplazo | Y14: Gabriel De Angelis | AA14: Inderminado | AD14: L a V de 9h a 18h | AE14: La Musa | AG14: 46076 | AJ14: Juan Pablo Ratuszniak | AK14: 1800000 Neto | Bruto 2.168.675 | AL14: FUCO | AM14: Ok | AN14: SI | AO14: 14/11 se reclama agenda a Damián por entrevistas, 20/11 Damián conoce 2 candidatos / 25-11 Damian selecciona un candidato. El candidato se baja por mejora salarial en su trabajo. Se baja del proceso. Reinicia la busqueda /Nuestra propuesta 2 millones en mano + comisiones.
A15: 00014 | B15: 45897 | C15: =IF(B15="","",IF(OR(TRIM(R15)="En curso",TRIM(R15)="En proceso de ingreso"),TODAY()-B15,"Cerrada")) -> Cerrada | D15: Jose | E15: Aprobada | J15: PREPAGA | K15: Cobensil | L15: Cobranzas | M15: Facturación y Cobranzas | N15: Liderazgo | O15: Supervisor/a de facturación y cobranzas | P15: Rodríguez | R15: Cerrada | S15: Ingreso | W15: Apertura de puesto | AA15: Inderminado | AD15: L a V de 09h a 18h | AE15: Ravignani | AF15: 46007 | AG15: 46024 | AJ15: Paula García | AK15: 1.800.000$ netos | AL15: FUCO | AO15: 25/11/2025 se presenta una terna de 3 candidatos a Florencia Rodriguez, 05/12 conoció a Paula Garcia, 09/12 fue derivada a psico y preo
A16: 00015 | B16: 45916 | C16: =IF(B16="","",IF(OR(TRIM(R16)="En curso",TRIM(R16)="En proceso de ingreso"),TODAY()-B16,"Cerrada")) -> Cerrada | D16: Jose | E16: Cancelada | J16: Centros Ambulatorios | L16: Mantenimiento | M16: Servicios de Apoyo | N16: Liderazgo | O16: Jefe/a de Mantenimiento | P16: Porretti | R16: Cancelada | S16: Cancelada | U16: Alta | V16: Baja | W16: Apertura de puesto | AA16: Inderminado | AD16: Lunes a Viernes 9 a 18 hs | AK16: $ 3.253.012,05 bruto / $ 2.700.000 neto | AL16: FUCO | AO16: Nicolas Ruiz no apto Labo / 1 candidato en curso OK - banda 3 k brutos . Se presentará dos candidatos que no tienen formación requerida para contemplarlos en el análisis
A17: 00016 | B17: 45931 | C17: =IF(B17="","",IF(OR(TRIM(R17)="En curso",TRIM(R17)="En proceso de ingreso"),TODAY()-B17,"Cerrada")) -> Cerrada | D17: Ema | E17: Aprobada | J17: SANATORIO COLEGIALES | K17: CIRENDSA | L17: Traumatología | M17: Guardia | N17: Asistencial/Médicos | O17: MEDICO/A | P17: Faiman | R17: Cerrada | S17: Ingreso | W17: Reemplazo | AA17: Plazo Fijo | AD17: MARTES 8 A 20 HS | AE17: SANATORIO | AF17: 45974 | AG17: 46028 | AJ17: SAMMY OSPINA | AK17: $977.367,60 bruto / $796.554,59 neto | AL17: AMAP | AM17: NO | AO17: M8-20 - Esperando certificado especialista // 18-12 recibe el certificado de especialdiad // 22-12 contacto con Faiman para definir ingreso // 26-12 confirma su ingreso
A18: 00017 | B18: 45943 | C18: =IF(B18="","",IF(OR(TRIM(R18)="En curso",TRIM(R18)="En proceso de ingreso"),TODAY()-B18,"Cerrada")) -> Cerrada | D18: Jose | E18: Aprobada | J18: SANATORIO COLEGIALES | L18: Comercial | M18: Administración y Finanzas | N18: Liderazgo | O18: Responsable de Ventas Institucionales | P18: Poeta | R18: Cerrada | S18: Ingreso | W18: Reemplazo | Y18: Leandro Gómez | AA18: Inderminado | AG18: 46027 | AJ18: FLorencia Fernandez ( Promoción) | AO18: 19/11 psicotecnico Florencia Fernández actual solaboradora del área / Buscar reemplazo: se presenta 25/11
A19: 00018 | B19: 45945 | C19: =IF(B19="","",IF(OR(TRIM(R19)="En curso",TRIM(R19)="En proceso de ingreso"),TODAY()-B19,"Cerrada")) -> Cerrada | D19: Franco | E19: Aprobada | J19: SANATORIO COLEGIALES | K19: Cirenda | L19: Procesos Retributivos | M19: Administración y Finanzas | N19: Administrativo/a | O19: FACTURISTA | P19: Alvarez | R19: Cerrada | S19: Ingreso | W19: Reemplazo | AA19: Eventual | AD19: Lunes a Viernes de 9 a 18hs | AE19: Sanatorio | AF19: 46027 | AG19: 46034 | AJ19: Anabella Belen Pantano | AK19: $1.207.568,30 Bruto / $1.008.912,50 neto | AL19: 122 | AM19: No | AN19: No | AO19: Débitos
A20: 00019 | B20: 45957 | C20: =IF(B20="","",IF(OR(TRIM(R20)="En curso",TRIM(R20)="En proceso de ingreso"),TODAY()-B20,"Cerrada")) -> Cerrada | D20: Franco | E20: Aprobada | J20: CORPO | K20: Desarollos en salud | L20: Comercial | M20: Administración y Finanzas | N20: Administrativo/a | O20: Administrativo/a comercial | P20: Poeta | R20: Cerrada | S20: Ingreso | W20: Reemplazo | Y20: Florencia Anahi Fernandez (157891) | AA20: Plazo Fijo | AD20: Lunes a Viernes de 9 a 18hs | AE20: La Musa y Sanatorio | AF20: 46021 | AG20: 46034 | AJ20: Yamila Genaisir | AK20: $1.584.578,31 bruto / $1.315.200,00 Neto | AL20: FUCO | AM20: Si | AN20: NO | AO20: Puesto: Administrativa de presupuestos. Reemplaza a Florencia por ascenso de esta misma.
A21: 00020 | B21: 45957 | C21: =IF(B21="","",IF(OR(TRIM(R21)="En curso",TRIM(R21)="En proceso de ingreso"),TODAY()-B21,"Cerrada")) -> Cerrada | D21: Franco | E21: Aprobada | J21: CMV | K21: CMV | L21: Administración y Finanzas | M21: Administración y Finanzas | N21: Administrativo/a | O21: Administrativo/a Contable | P21: Rea | R21: Cerrada | S21: Ingreso | W21: Reemplazo | Y21: Agudelo | AA21: Inderminado | AD21: Lunes a Viernes de 9 a 18hs | AE21: CMV | AF21: 46049 | AG21: 46056 | AJ21: Melanie Laffon | AK21: $1.300.000 neto | AL21: FUCO | AM21: NO | AN21: NO | AO21: 20/11 - Eugenia conoce un candidato, el candidato cancela entrevista, 27/11 - Eugenia en conjunto con Rrhh conocera a 2 candidatos. 2 candidatas en preoc. Iba a ingresar el dia 6/1/25 una candidata pero no se presento. Ese mismo dia se retoma busqueda de perfiles. Se avanza con Melanie Laffon
A22: 00021 | B22: 45962 | C22: =IF(B22="","",IF(OR(TRIM(R22)="En curso",TRIM(R22)="En proceso de ingreso"),TODAY()-B22,"Cerrada")) -> Cerrada | D22: Ema | E22: Aprobada | J22: SANATORIO COLEGIALES | K22: CIRENDSA | L22: Hotelería | M22: Internación | N22: Servicios Generales | O22: MUCAMO/A | P22: Valeria Dodero | R22: Cerrada | S22: Ingreso | W22: Reemplazo | Y22: Libramento T | AA22: Eventual | AD22: 14-22 HS | AE22: SANATORIO | AF22: 46021 | AG22: 46028 | AJ22: LEONOR ORELLANA | AK22: $1.000.154,62 bruto / $830.004,50 NETO | AL22: 122/75 | AM22: no | AO22: 18-12 8 perfiles en preoc / 30-12 apto
A23: 00022 | B23: 45962 | C23: =IF(B23="","",IF(OR(TRIM(R23)="En curso",TRIM(R23)="En proceso de ingreso"),TODAY()-B23,"Cerrada")) -> Cerrada | D23: Ema | E23: Aprobada | J23: SANATORIO COLEGIALES | K23: CIRENDSA | L23: Kinesiología | M23: Terapia Intensiva | N23: Asistencial/Otros | O23: KINESIOLOGO/A | P23: Laredo | R23: Cerrada | S23: Ingreso | W23: Reemplazo | Y23: Menchon J | AA23: Plazo Fijo | AD23: Lunes a Viernes 14 a 20 hs, 1 Sábado y Domingo al mes 8 a 20 hs. Feriado rotativo | AE23: SANATORIO | AF23: 46015 | AG23: 46028 | AJ23: ARACELI SARMIENTO | AK23: $1.962.564,65 bruto / $1.628.956,00 neto | AL23: 122/75 | AM23: NO | AO23: 12/11 Marcos T. - 13/11 18/11 Cvs no avanzan - 28/11 entrevista Lucas M decide no avanzar - 4/12 Patricio M no asiste // 12-12 entrevista Araceli / 18-12 Araceli en preo
A24: 00023 | B24: 45962 | C24: =IF(B24="","",IF(OR(TRIM(R24)="En curso",TRIM(R24)="En proceso de ingreso"),TODAY()-B24,"Cerrada")) -> Cerrada | D24: Ema | E24: Aprobada | J24: SANATORIO COLEGIALES | K24: CIRENDSA | L24: Enfermeria | M24: Terapia Intensiva | N24: Asistencial/Enfermería | O24: Enfermero/a de Terapia Intensiva | P24: Alvez | R24: Cerrada | S24: Ingreso | W24: Reemplazo | Y24: Camino C | AA24: Eventual | AD24: 22 A 6 HS | AE24: SANATORIO | AF24: 46049 | AG24: 46055 | AJ24: STEPHANIE VERA | AK24: $1.554.520,85 bruto / $1.295.707,00 neto | AL24: 122/75 | AM24: NO | AO24: 11/11 entrevista. Perfiles sólo de CM. 20/11 entrevista. No gustaron los perfiles UTI/UCO - 03/12 entrevista. Ninguno con experiencia en UTI/UCO asistió. Agendando nueva entrevista / 6 candidatos en preocupacional
A25: 00024 | B25: 45962 | C25: =IF(B25="","",IF(OR(TRIM(R25)="En curso",TRIM(R25)="En proceso de ingreso"),TODAY()-B25,"Cerrada")) -> Cerrada | D25: Ema | E25: Aprobada | J25: SANATORIO COLEGIALES | K25: CIRENDSA | L25: Enfermeria | M25: Terapia Intensiva | N25: Asistencial/Enfermería | O25: Enfermero/a de Terapia Intensiva | P25: Alvez | R25: Cerrada | S25: Ingreso | W25: Reemplazo | Y25: Ibarra Gilda | AA25: Eventual | AD25: 22 A 6 HS | AE25: SANATORIO | AF25: 46049 | AG25: 46055 | AJ25: MARIA GONZALEZ | AK25: $1.554.520,85 bruto / $1.295.707,00 neto | AL25: 122/75 | AM25: NO | AO25: 11/11 entrevista. Perfiles sólo de CM. 20/11 entrevista. No gustaron los perfiles UTI/UCO - 03/12 entrevista. Ninguno con experiencia en UTI/UCO asistió. Agendando nueva entrevista / 6 candidatos en preocupacional
A26: 00025 | B26: 45962 | C26: =IF(B26="","",IF(OR(TRIM(R26)="En curso",TRIM(R26)="En proceso de ingreso"),TODAY()-B26,"Cerrada")) -> Cerrada | D26: Fer | E26: Aprobada | J26: CORPO | K26: Cober | L26: Gestión de las Personas | M26: Administración y Finanzas | N26: Analista | O26: Liquidador/a de sueldos | P26: Ezequiel | R26: Cerrada | S26: Ingreso | W26: Apertura de puesto | AA26: Inderminado | AD26: Lunes a viernes de 8 a 17hs | AE26: La Musa | AF26: 46027 | AG26: 46034 | AJ26: Eduardo Rodriguez Rosales | AK26: $2.000.000 neto | AL26: FUCO | AM26: Si | AN26: no | AO26: se conoció 1 candidato la primera semana de noviembre, se ajusta el perfil no jr, se sube la remuneración 1.7, se entrevistaron 3 candidatos/ se vuelve a ajusto el perfil diversidad de convios que venga de consultoras. Se derivo a consultora se ajusta salario a 2 M
A27: 00026 | B27: 45972 | C27: =IF(B27="","",IF(OR(TRIM(R27)="En curso",TRIM(R27)="En proceso de ingreso"),TODAY()-B27,"Cerrada")) -> Cerrada | D27: Jose | E27: Aprobada | J27: LABBO | K27: Argil | L27: Laboratorio | M27: Operaciones | N27: Asistencial/Otros | O27: BIOQUIMICO/A | P27: Mercedes | R27: Cerrada | S27: Ingreso | W27: Reemplazo | Y27: Mercdes Miglianone | AA27: Plazo Fijo | AD27: L a V 12h a 18h, Sábado fléxibles | AE27: Argil | AF27: 46017 | AG27: 46040 | AJ27: Valeria Cánovas | AK27: 2.300.000$ Netos | AL27: FUCO | AO27: 25/11 entrevistas, 12/12 Avanza a psico y preo Valeria Cánovas
A28: 00027 | B28: 45973 | C28: =IF(B28="","",IF(OR(TRIM(R28)="En curso",TRIM(R28)="En proceso de ingreso"),TODAY()-B28,"Cerrada")) -> Cerrada | D28: Franco | E28: Aprobada | J28: CORPO | L28: Comunicación | M28: Marketing | N28: Analista | O28: Analista de marketing | P28: Pachelo | R28: Cerrada | S28: Ingreso | W28: Reemplazo | Y28: Camila Osa | AA28: Inderminado | AD28: Lunes a viernes de 9 a 18hs | AE28: Cramer | AF28: 46063 | AG28: 46076 | AJ28: Candela Fernandez | AK28: $1.600.000 neto | AL28: FUCO | AM28: Si. (Pedido lunes 09/02/26) | AN28: NO | AO28: 18/11 - se envía 6 perfiles a Pachelo, se acuerda esperar el retorno de Lucía de vacaciones para avanzar con entrevista grupal, 4/12 entrevista con 3 candidatos - mencionan que les enviemos mas perfiles para tomar una decision, 9/12 se envian por mail 4 cv's para su analisis y poder coordinar entrevistas. 22/12 Se envia feedback a F.Pachelo de las entrevistas de 3 candidatos que nos gustaron luego de realizar entrevistas. / Pachelo selecciona a una candidata + Tenemos 1 backup. Se avanza con Guadalupe Diaz Bo el 23-01-26, 28-01-26 se recibe preoc no apto. En paralelo, se envia a entrevista con F.Pachelo candidata de back up el dia 29-01-26. Se avanza con la candidata de back up Candela Fernandez a preoc.
A29: 00028 | B29: 45975 | C29: =IF(B29="","",IF(OR(TRIM(R29)="En curso",TRIM(R29)="En proceso de ingreso"),TODAY()-B29,"Cerrada")) -> Cerrada | D29: Ema | E29: Aprobada | J29: CMV | K29: CMV | L29: Administración | M29: Administración | N29: Especialista | O29: CONTADOR/A | P29: Colalillo | R29: Cerrada | S29: Ingreso | W29: Reemplazo | Y29: Eugenia Rea | Z29: Desvinculación empresa | AA29: Inderminado | AD29: Lunes a viernes de 9 a 18hs | AE29: LA MUSA | AF29: 46080 | AG29: 46084 | AJ29: JESICA SEGOVIA | AK29: $ 3.132.530,12 bruto / $ 2.600.000 neto | AL29: FUCO | AM29: Si. (Pedido Viernes 27/2) | AN29: NO | AO29: 14/11 relevamiento perfil claudia / 25/11 lectura de cvs / 4/12 3 entrevistas RRHH / 05/12 perfiles enviados a Claudio / 12/12 Claudio solicita entrevistar - 15 a 19/12 Claudio vacaciones / Claudio entrvistatará 2 candidatos ,semana del 26/01 - 02/02 preo y psico / 18/02 - No se generó la vacante
A30: 00029 | B30: 45975 | C30: =IF(B30="","",IF(OR(TRIM(R30)="En curso",TRIM(R30)="En proceso de ingreso"),TODAY()-B30,"Cerrada")) -> Cerrada | D30: Franco | E30: Aprobada | J30: SANATORIO COLEGIALES | K30: Desarollos en salud | L30: Sistemas | M30: Sistemas | N30: Pasante/Becario | O30: Pasante | P30: Gatica | R30: Cerrada | S30: Ingreso | W30: Apertura de puesto | AA30: Inderminado | AD30: 20hs semanales, con horario a coordinar | AE30: SANATORIO | AF30: 46027 | AG30: 46041 | AJ30: Vicente D’Annunzio | AK30: $388.330,00 bruto | AM30: NO | AN30: NO
A31: 00030 | B31: 45975 | C31: =IF(B31="","",IF(OR(TRIM(R31)="En curso",TRIM(R31)="En proceso de ingreso"),TODAY()-B31,"Cerrada")) -> Cerrada | D31: Franco | E31: Aprobada | J31: SANATORIO COLEGIALES | L31: Sistemas | M31: Servicios de Apoyo | N31: Pasante/Becario | O31: Pasante | P31: Gatica | R31: Cerrada | S31: Ingreso | W31: Apertura de puesto | AA31: Inderminado | AF31: 46027 | AG31: 46041 | AJ31: VICENTE D´ANUNZIO | AO31: 4/12 se entrevistan 2 candidatos pero el referente solicita conocer mas candidatos para tomar una decision, 16/12 se conoce un candidato, 18/12 se conoce otro candidato. 22/12 se envia a preoc un candidato
A32: 00031 | B32: 45980 | C32: =IF(B32="","",IF(OR(TRIM(R32)="En curso",TRIM(R32)="En proceso de ingreso"),TODAY()-B32,"Cerrada")) -> Cerrada | D32: Ema | E32: Aprobada | J32: SANATORIO COLEGIALES | K32: CIRENDSA | L32: Admisión | M32: Consultorios Externos | N32: Administrativo/a | O32: ADMISIONISTA | P32: Gomez | R32: Cerrada | S32: Ingreso | W32: Apertura de puesto | Y32: 5° admin PB Laboratorio | AA32: Plazo Fijo | AD32: Lunes a Viernes 8 a 16 hs. Sabado por medio 7 a 15 hs | AE32: SANATORIO | AF32: 46037 | AG32: 46045 | AJ32: VALENTINA RAMIREZ | AK32: $1.164.203,77 bruto / $976.802,50 neto | AL32: 122/75 | AM32: NO | AO32: 05-12 Perfil entrevista ok 08-12 se baja del proceso. 11-12 entrevista. Sin exp real en labo. 17-12 1 perfil ok pero vive en Tigre. Evaluando otras opciones
A33: 00032 | B33: 45985 | C33: =IF(B33="","",IF(OR(TRIM(R33)="En curso",TRIM(R33)="En proceso de ingreso"),TODAY()-B33,"Cerrada")) -> Cerrada | D33: Franco | E33: Aprobada | J33: SANATORIO COLEGIALES | K33: CIRENDSA | L33: Operaciones | M33: Servicios de Apoyo | N33: Servicios Generales | O33: PEON | P33: Cordoba | R33: Cerrada | S33: Ingreso | W33: Reemplazo | Y33: Vacaciones | AA33: Eventual | AD33: ROTATIVO entre 6-14 hs/14-22 hs/22-6 hs segun cronograma | AE33: SANATORIO | AF33: 46024 | AG33: 46034 | AJ33: MAXIMILIANO GUTIERREZ NICOLAS MEDINA LIHUEL RODRIGUEZ | AK33: $1.000.254,62 bruto / $830.085,50 neto | AL33: 122/75 | AM33: NO | AO33: 12/12 6 perfiles citados, asisten 4 y 2 pasan a preo 17/12 asiste uno solo - Entrevista 22/12 // 1 PERFIL APTO 30-12
A34: 00033 | B34: 45986 | C34: =IF(B34="","",IF(OR(TRIM(R34)="En curso",TRIM(R34)="En proceso de ingreso"),TODAY()-B34,"Cerrada")) -> Cerrada | D34: Jose | E34: Aprobada | J34: CORPO | K34: Healthnes | L34: Gestión del Cambio | M34: Administración | N34: Analista | O34: Analista de Procesos | P34: Rodríguez M | R34: Cerrada | S34: Ingreso | W34: Apertura de puesto | AA34: Inderminado | AD34: L a V 09h a 18h | AE34: Cramer | AF34: 46035 | AG34: 46041 | AJ34: Romina Cecchin | AK34: 2.500.000 $ NETOS | AL34: FUCO | AO34: jueves 11/12 María se reune con Emilio para definir quien avanza, 18/12 Hace psico Romina | 12/01 - 1 candidata en preocupacional, fecha de ingreso (probable) - semana 18/01
A35: 00034 | B35: 45986 | C35: =IF(B35="","",IF(OR(TRIM(R35)="En curso",TRIM(R35)="En proceso de ingreso"),TODAY()-B35,"Cerrada")) -> Cerrada | D35: Ema | E35: Aprobada | J35: FARMACIA | K35: NOBEL | L35: Administración y Finanzas | M35: Farmacia Lamaité | N35: Liderazgo | O35: Supervisor/a de Farmacia | P35: Emilio | R35: Cerrada | S35: Ingreso | W35: Reemplazo | Y35: Iván Lara | AA35: Inderminado | AD35: 48 hs semanales de Lunes a Sabado | AE35: LAMAITE | AF35: 46035 | AG35: 46041 | AJ35: SERGIO BERNIGAUD | AK35: $2.000.000 neto | AL35: FUCO | AM35: SI | AO35: 4/12 Entrevista - 5/12 entrevista - 13/12 entrevista Cecilia - 16/12 2 entrevistas - 18/12 entrevista Sergio + 1 perfil consultora conocido 19/12 - 23/12 entrevista Sergio
A36: 00035 | B36: 45986 | C36: =IF(B36="","",IF(OR(TRIM(R36)="En curso",TRIM(R36)="En proceso de ingreso"),TODAY()-B36,"Cerrada")) -> Cerrada | D36: Fer | E36: Aprobada | J36: CORPO | K36: Healtnes | L36: Contact Center | M36: Servicios de Apoyo | N36: Liderazgo | O36: Coordinador/a de Contac Center | P36: Nahir | R36: Cerrada | S36: Ingreso | W36: Reemplazo | Y36: Agostina Zowkoski | AA36: Inderminado | AD36: Lunes a Viernes de 8 a 5hs | AE36: Maure | AF36: 46028 | AG36: 46041 | AJ36: Agustina Campos | AK36: $2200000 neto | AL36: FUCO | AM36: Si | AN36: No | AO36: Se envió 12-12 2 perfiles para entrevista técnica, se entrevisto 17-12 Agustina Campos, pasa a psico el 19-12, se suien evalaundo candidatos
A37: 00036 | B37: 45987 | C37: =IF(B37="","",IF(OR(TRIM(R37)="En curso",TRIM(R37)="En proceso de ingreso"),TODAY()-B37,"Cerrada")) -> Cerrada | D37: Ema | E37: Aprobada | J37: SANATORIO COLEGIALES | L37: Enfermeria | M37: Internación | N37: Asistencial/Enfermería | O37: Enfermero/a de Quimio | P37: Alvez | R37: Cerrada | S37: Ingreso | W37: Reemplazo | Y37: Mazars | AA37: Inderminado | AG37: 46076 | AJ37: YAEL | AO37: L-V 12 a 18h / Pase interno de Piñeiro Y.
A38: 00037 | B38: 45991 | C38: =IF(B38="","",IF(OR(TRIM(R38)="En curso",TRIM(R38)="En proceso de ingreso"),TODAY()-B38,"Cerrada")) -> Cerrada | D38: Ema | E38: Aprobada | J38: SANATORIO COLEGIALES | K38: CIRENDSA | L38: Cirugía | M38: Quirófano | N38: Asistencial/Otros | O38: INSTRUMENTADOR/A | P38: Di Franco | R38: Cerrada | S38: Ingreso | W38: Reemplazo | Y38: Otero R | AA38: Plazo Fijo | AD38: Lunes a Sabados 14 a 22 hs. Feriado rotativo | AE38: SANATORIO | AF38: 46027 | AG38: 46041 | AJ38: AYELEN CARRUBBA | AK38: $1.478.071,38 bruto / $1.230.851,50 neto | AL38: 122/75 | AM38: NO | AO38: 18-12 entrevistas 19-12 Entrevista Ale. Agendando preocupacional 23-12
A39: 00038 | B39: 45994 | C39: =IF(B39="","",IF(OR(TRIM(R39)="En curso",TRIM(R39)="En proceso de ingreso"),TODAY()-B39,"Cerrada")) -> Cerrada | D39: Fer | E39: Aprobada | J39: CORPO | K39: Cober | L39: Gestión de las Personas | M39: Administración y Finanzas | N39: Liderazgo | O39: Coordinador/a de atracción de talento | P39: Daniela | R39: Cerrada | S39: Ingreso | W39: Reemplazo | Y39: Alejandro Alzate | AA39: Inderminado | AD39: Lunes a viernes de 8 a 17hs | AE39: La musa | AF39: 46020 | AG39: 46027 | AJ39: Juan Pablo Sanchez | AK39: 2800000 bruto | AL39: FUCO | AM39: Si
A40: 00039 | B40: 45994 | C40: =IF(B40="","",IF(OR(TRIM(R40)="En curso",TRIM(R40)="En proceso de ingreso"),TODAY()-B40,"Cerrada")) -> Cerrada | D40: Franco | E40: Aprobada | J40: PREPAGA | K40: Cobensil | L40: Cobranzas | M40: Administración y Finanzas | N40: Comercial, ventas y cobranzas | O40: Cobrador/a | P40: Florencia Rodriguez | R40: Cerrada | S40: Ingreso | W40: Reemplazo | Y40: Milenka Barsallo | AA40: Inderminado | AD40: Lunes a Viernes de 11 a 20hs. (Full time) | AE40: Ravignani | AF40: 46020 | AG40: 46028 | AJ40: Romina Llanos | AK40: $1.264.540,33 bruto / $1.033.022,00 neto | AL40: 130/75 | AM40: No | AN40: NO | AO40: 12/12 - Se conocen 3 candidatos, se avanzan con los 3 a preoc.
A41: 00040 | B41: 46000 | C41: =IF(B41="","",IF(OR(TRIM(R41)="En curso",TRIM(R41)="En proceso de ingreso"),TODAY()-B41,"Cerrada")) -> Cerrada | D41: Ema | E41: Aprobada | J41: SANATORIO COLEGIALES | K41: CIRENDSA | L41: Cirugía | M41: Quirófano | N41: Asistencial/Otros | O41: INSTRUMENTADOR/A | P41: Di Franco | R41: Cerrada | S41: Ingreso | W41: Reemplazo | Y41: Suarez C | AA41: Eventual | AD41: Lunes a Sábados 15 a 23 hs. Feriados rotativos. | AE41: SANATORIO | AF41: 46027 | AG41: 46034 | AJ41: YEISON TEJADA | AK41: $1.478.071,38 bruto $1.230.851,50 neto | AL41: 122/75 | AM41: No
A42: 00041 | B42: 46000 | C42: =IF(B42="","",IF(OR(TRIM(R42)="En curso",TRIM(R42)="En proceso de ingreso"),TODAY()-B42,"Cerrada")) -> Cerrada | D42: Franco | E42: Aprobada | G42: No | J42: PREPAGA | K42: Cobensil SA | L42: Ventas Retail | M42: Comercial | N42: Comercial, ventas y cobranzas | O42: VENDEDOR/A | P42: Serafin | R42: Cerrada | S42: Ingreso | W42: Reemplazo | Y42: REA, ALEX JUAN ARIEL | AA42: Inderminado | AD42: Lunes a Viernes de 10 a 18hs | AE42: Sede de Vicente Lopez (Av. Maipu 1680) | AF42: 46044 | AG42: 46056 | AJ42: Adrian Torosantucci | AK42: $1.271.329,36 bruto / $1.036.688,00 neto | AL42: 130/75 | AM42: No | AN42: No
A43: 00042 | B43: 46000 | C43: =IF(B43="","",IF(OR(TRIM(R43)="En curso",TRIM(R43)="En proceso de ingreso"),TODAY()-B43,"Cerrada")) -> Cerrada | D43: Ema | E43: Aprobada | J43: SANATORIO COLEGIALES | K43: CIRENDSA | L43: Hotelería | M43: Internación | N43: Servicios Generales | O43: MUCAMO/A | P43: Valeria Dodero | R43: Cerrada | S43: Ingreso | W43: Reemplazo | Y43: Amarilla R | AA43: Eventual | AD43: 14-22 | AE43: SANATORIO | AF43: 46028 | AG43: 46041 | AJ43: MARISA MARQUEZ | AK43: $1.000.154,62 BRUTO / $830.004,50 NETO | AL43: 122/75 | AM43: NO | AO43: 17-12 entrevista 23-12 preoc // No firmó Anahi Gonzalez 6-1
A44: 00043 | B44: 46000 | C44: =IF(B44="","",IF(OR(TRIM(R44)="En curso",TRIM(R44)="En proceso de ingreso"),TODAY()-B44,"Cerrada")) -> Cerrada | D44: Ema | E44: Aprobada | J44: SANATORIO COLEGIALES | K44: CIRENDSA | L44: Cirugía | M44: Quirófano | N44: Asistencial/Otros | O44: INSTRUMENTADOR/A | P44: Di Franco | R44: Cerrada | S44: Ingreso | W44: Reemplazo | Y44: Karen G | AA44: Plazo Fijo | AD44: Lunes a Sábados 14 a 22 hs. Feriados rotativos. | AE44: SANATORIO | AF44: 46027 | AG44: 46034 | AJ44: CAROLINA CAMPOS | AK44: $1.478.071,38 bruto / $1.230.851,50 neto | AL44: 122/75 | AM44: NO | AO44: 18/12 entrevista
A45: 00044 | B45: 46002 | C45: =IF(B45="","",IF(OR(TRIM(R45)="En curso",TRIM(R45)="En proceso de ingreso"),TODAY()-B45,"Cerrada")) -> Cerrada | D45: Fer | E45: Aprobada | J45: CORPO | K45: Healtnes | L45: Mantenimiento | M45: Servicios de Apoyo | N45: Especialista | O45: ARQUITECTO/A | P45: Emilio | R45: Cerrada | S45: Ingreso | W45: Reemplazo | Y45: Nestor Toledo | AA45: Inderminado | AD45: a coordinar | AE45: Cramer | AF45: 46062 | AG45: 46071 | AJ45: Luciana Bruno | AK45: $3000000 bruto | AL45: FUCO | AM45: Si | AN45: no | AO45: se publica ne linkedin 18-12, 30-12 se entrevistaron 2 perfiles, se pasa a Dani para 2da instancia Cecilia Ibarola y Luciana Bruno | 12/01 - pidiendo referencias. Pasa Luciana a preocupacional el 27-01
A46: 00045 | B46: 46004 | C46: =IF(B46="","",IF(OR(TRIM(R46)="En curso",TRIM(R46)="En proceso de ingreso"),TODAY()-B46,"Cerrada")) -> Cerrada | D46: Ema | E46: Aprobada | J46: SANATORIO COLEGIALES | K46: CIRENDSA | L46: Enfermeria | M46: Terapia Intensiva | N46: Asistencial/Enfermería | O46: Enfermero/a de Terapia Intensiva | P46: Alvez | R46: Cerrada | S46: Ingreso | W46: Reemplazo | Y46: Pistan D | AA46: Eventual | AD46: 14 A 22 HS por vacaciones | AE46: SANATORIO | AF46: 46049 | AG46: 46055 | AJ46: FISDERI VASQUEZ | AK46: $1.444.204,15 bruto / $1.205.247,26 neto | AL46: 122/75 | AM46: NO | AO46: Agendando una nueva entrevista
A47: 00046 | B47: 46004 | C47: =IF(B47="","",IF(OR(TRIM(R47)="En curso",TRIM(R47)="En proceso de ingreso"),TODAY()-B47,"Cerrada")) -> Cerrada | D47: Ema | E47: Aprobada | J47: SANATORIO COLEGIALES | K47: CIRENDSA | L47: Enfermeria | M47: Terapia Intensiva | N47: Asistencial/Enfermería | O47: Enfermero/a de Terapia Intensiva | P47: Alvez | R47: Cerrada | S47: Ingreso | W47: Reemplazo | Y47: Loza J | AA47: Eventual | AD47: 14 A 22 HS por vacaciones | AE47: SANATORIO | AF47: 46049 | AG47: 46055 | AJ47: GERALDINE CASTRO | AK47: $1.444.204,15 bruto / $1.205.247,26 neto | AL47: 122/75 | AM47: NO | AO47: Agendando una nueva entrevista
A48: 00047 | B48: 46006 | C48: =IF(B48="","",IF(OR(TRIM(R48)="En curso",TRIM(R48)="En proceso de ingreso"),TODAY()-B48,"Cerrada")) -> Cerrada | D48: Franco | E48: Aprobada | J48: SANATORIO COLEGIALES | K48: CIRENDSA | L48: Mantenimiento | M48: Servicios de Apoyo | N48: Mantenimiento y obras | O48: OFICIAL DE MANTENIMIENTO | P48: Erika | R48: Cerrada | S48: Ingreso | W48: Reemplazo | Y48: ROMIG, JAVIER ALEJANDRO | AA48: Plazo Fijo | AD48: Lunes a Sabados de 6 a 14hs | AE48: SANATORIO | AF48: 46020 | AG48: 46034 | AJ48: Sergio Leguizamon | AK48: $1.169.901,95 bruto / $966.949,00 neto | AL48: 122/75 | AM48: NO | AN48: NO | AO48: 18/12 Entrevista en conjunto con Erika, se conocen 3 candidatos, avanzan 2 a preoc.
A49: 00048 | B49: 46006 | C49: =IF(B49="","",IF(OR(TRIM(R49)="En curso",TRIM(R49)="En proceso de ingreso"),TODAY()-B49,"Cerrada")) -> Cerrada | D49: Franco | E49: Aprobada | J49: SANATORIO COLEGIALES | K49: CIRENDSA | L49: Mantenimiento | M49: Servicios de Apoyo | N49: Mantenimiento y obras | O49: OFICIAL DE MANTENIMIENTO | P49: Erika | R49: Cerrada | S49: Ingreso | W49: Reemplazo | AA49: Plazo Fijo | AD49: Lunes a Sabados de 6 a 14hs | AE49: SANATORIO | AF49: 46028 | AG49: 46034 | AJ49: Braian Miguel Rojas | AK49: $1.169.901,95 bruto / $966.949,00 neto | AL49: 122/75 | AM49: NO | AN49: NO | AO49: 18/12 Entrevista en conjunto con Erika, se conocen 3 candidatos, avanzan 2 a preoc. / inicialmente la búsqueda se genera por Gustavo Razzetto , ingresa Brian Miguel quién renuncia a los 2 días .
A50: 00049 | B50: 46007 | C50: =IF(B50="","",IF(OR(TRIM(R50)="En curso",TRIM(R50)="En proceso de ingreso"),TODAY()-B50,"Cerrada")) -> Cerrada | D50: Ema | E50: Aprobada | J50: SANATORIO COLEGIALES | K50: CIRENDSA | L50: Enfermeria | M50: Terapia Intensiva | N50: Asistencial/Enfermería | O50: Enfermero/a de Terapia Intensiva | P50: Alvez | R50: Cerrada | S50: Ingreso | U50: Baja | V50: Media | W50: Reemplazo | Y50: Roque J | AA50: Inderminado | AD50: 14-22 | AE50: SANATORIO | AF50: 46092 | AG50: 46104 | AJ50: WENDY ASTORGA | AK50: $1.444.204,15 bruto / $1.205.247,26 neto | AL50: 122/75 | AM50: NO | AN50: NO
A51: 00050 | B51: 46009 | C51: =IF(B51="","",IF(OR(TRIM(R51)="En curso",TRIM(R51)="En proceso de ingreso"),TODAY()-B51,"Cerrada")) -> Cerrada | D51: Ema | E51: Aprobada | J51: SANATORIO COLEGIALES | K51: CIRENDSA | L51: Hotelería | M51: Internación | N51: Servicios Generales | O51: MUCAMO/A | P51: Valeria Dodero | R51: Cerrada | S51: Ingreso | W51: Reemplazo | Y51: Segovia M | AA51: Plazo Fijo | AD51: 14-22 | AE51: SANATORIO | AF51: 46027 | AG51: 46028 | AJ51: NILDA SANTACRUZ | AK51: $1.000.154,62 BRUTO / $830.004,50 NETO | AL51: 122/75 | AM51: NO | AO51: 17-12 entrevista 23-12 preoc
A52: 00051 | B52: 46009 | C52: =IF(B52="","",IF(OR(TRIM(R52)="En curso",TRIM(R52)="En proceso de ingreso"),TODAY()-B52,"Cerrada")) -> Cerrada | D52: Ema | E52: Aprobada | J52: SANATORIO COLEGIALES | K52: CIRENDSA | L52: Hotelería | M52: Internación | N52: Servicios Generales | O52: MUCAMO/A | P52: Valeria Dodero | R52: Cerrada | S52: Ingreso | W52: Reemplazo | Y52: Ledesma M | AA52: Plazo Fijo | AD52: 14-22 | AE52: SANATORIO | AF52: 46027 | AG52: 46028 | AJ52: ANA ODRIOZOLA | AK52: $1.000.154,62 BRUTO / $830.004,50 NETO | AL52: 122/75 | AM52: NO | AO52: 17-12 entrevista 23-12 preoc
A53: 00052 | B53: 46010 | C53: =IF(B53="","",IF(OR(TRIM(R53)="En curso",TRIM(R53)="En proceso de ingreso"),TODAY()-B53,"Cerrada")) -> Cerrada | D53: Ema | E53: Aprobada | J53: SANATORIO COLEGIALES | K53: CIRENDSA | L53: Enfermeria | M53: Internación | N53: Asistencial/Enfermería | O53: Enfermero/a de Internación | P53: Alvez | R53: Cerrada | S53: Ingreso | W53: Reemplazo | Y53: Lic prolongada Montaño K | AA53: Eventual | AD53: 14 A 22 HS por cobertura licencia 129016 HERBAS BELEN | AE53: SANATORIO | AF53: 46037 | AG53: 46055 | AJ53: BRIGHIT FLORES | AK53: $1.223.571,44 bruto / $1.024.328,50 neto | AL53: 122/75 | AM53: NO
A54: 00053 | B54: 46011 | C54: =IF(B54="","",IF(OR(TRIM(R54)="En curso",TRIM(R54)="En proceso de ingreso"),TODAY()-B54,"Cerrada")) -> Cerrada | D54: Franco | E54: Aprobada | J54: SANATORIO COLEGIALES | K54: Desarrollos en salud | L54: Obras | M54: Servicios de Apoyo | N54: Mantenimiento y obras | O54: Albañil | P54: Tejedor | R54: Cerrada | S54: Ingreso | W54: Reemplazo | Y54: 162934 - Duarte Oscar | AA54: Inderminado | AD54: Lunes a Viernes de 8 a 17hs | AE54: Sanatorio | AF54: 46030 | AG54: 46041 | AJ54: Cristian Aguilar | AK54: $1.169.647,23 bruto / $979.266,50 neto | AL54: 122/75 | AM54: No | AN54: No | AO54: Entrevista 29/12, se envian a preoc a 2 candidatos
A55: 00054 | B55: 46011 | C55: =IF(B55="","",IF(OR(TRIM(R55)="En curso",TRIM(R55)="En proceso de ingreso"),TODAY()-B55,"Cerrada")) -> Cerrada | D55: Ema | E55: Aprobada | J55: SANATORIO COLEGIALES | K55: CIRENDSA | L55: Enfermeria | M55: Internación | N55: Asistencial/Enfermería | O55: Enfermero/a de Internación | P55: Alvez | R55: Cerrada | S55: Ingreso | W55: Reemplazo | Y55: Lic prolongada HerBas B | AA55: Eventual | AD55: 14 A 22 HS por cobertura licencia 130805 MONTAÑO KAREN | AE55: SANATORIO | AF55: 46037 | AG55: 46055 | AJ55: MARIANA CRISTALDO | AK55: $1.223.571,44 bruto / $1.024.328,50 neto | AL55: 122/75 | AM55: NO
A56: 00055 | B56: 46013 | C56: =IF(B56="","",IF(OR(TRIM(R56)="En curso",TRIM(R56)="En proceso de ingreso"),TODAY()-B56,"Cerrada")) -> Cerrada | D56: Ema | E56: Aprobada | J56: SANATORIO COLEGIALES | K56: CIRENDSA | L56: Enfermeria | M56: Terapia Intensiva | N56: Asistencial/Enfermería | O56: Enfermero/a de Terapia Intensiva | P56: Alvez | R56: Cerrada | S56: Ingreso | W56: Reemplazo | Y56: Vuelta Castellon Bassa a CM | AA56: Plazo Fijo | AD56: 22 A 6 HS | AE56: SANATORIO | AF56: 46072 | AG56: 46076 | AJ56: MARCOS IBARRA | AK56: $1.554.520,85 bruto / $1.295.707,00 neto | AL56: 122/75 | AM56: NO | AO56: CC TN
A57: 00056 | B57: 46013 | C57: =IF(B57="","",IF(OR(TRIM(R57)="En curso",TRIM(R57)="En proceso de ingreso"),TODAY()-B57,"Cerrada")) -> Cerrada | D57: Ema | E57: Aprobada | J57: SANATORIO COLEGIALES | K57: CIRENDSA | L57: Enfermeria | M57: Quirófano | N57: Asistencial/Enfermería | O57: Enfermero/a de Endoscopia | P57: Alvez | R57: Cerrada | S57: Ingreso | W57: Reemplazo | Y57: Piñeiro Y | AA57: Eventual | AD57: Lunes a Sábados 15 a 23 hs. Feriados a coordinar. | AE57: SANATORIO | AF57: 46049 | AG57: 46055 | AJ57: JUDITH CHAPOÑAN | AK57: $1.481.645,21 bruto / $1.235.949,00 neto | AL57: 122/75 | AM57: NO
A58: 00057 | B58: 46013 | C58: =IF(B58="","",IF(OR(TRIM(R58)="En curso",TRIM(R58)="En proceso de ingreso"),TODAY()-B58,"Cerrada")) -> Cerrada | D58: Franco | E58: Aprobada | G58: No | J58: PREPAGA | K58: Cobensil SA | L58: Ventas Retail | M58: Comercial | N58: Comercial, ventas y cobranzas | O58: VENDEDOR/A | P58: Serafin | R58: Cerrada | S58: Ingreso | W58: Reemplazo | Y58: CASTRO, SANDRA FLORENCIA | AA58: Inderminado | AD58: Lunes a Viernes de 10 a 18hs | AE58: Sede Colegiales (Lacroze 3257) | AF58: 46044 | AG58: 46056 | AJ58: Virginia Ivon Romero | AK58: $1.271.329,36 bruto / $1.036.688,00 neto | AL58: 130/75 | AM58: No | AN58: No
A59: 00058 | B59: 46013 | C59: =IF(B59="","",IF(OR(TRIM(R59)="En curso",TRIM(R59)="En proceso de ingreso"),TODAY()-B59,"Cerrada")) -> Cerrada | D59: Juanpi | E59: Aprobada | G59: No | H59: No | J59: PREPAGA | K59: Cobensil SA | L59: Business Inteligence | M59: Administración | N59: Analista IT | O59: Analista Business Analytics | P59: Ignacio Jaregui | R59: Cerrada | S59: Ingreso | U59: Alta | V59: Alta | W59: Reemplazo | Y59: Leandro Carbo | AA59: Indeterminado | AD59: Lunes a Viernes de 8 a 17hs / 9 a 18 hs | AE59: Ravignani | AF59: 46120 | AG59: 46132 | AH59: Externa | AI59: Consultora | AJ59: Rafael Valera | AK59: $2,800,000 ( Netos ) | AL59: FUCO | AM59: SI | AN59: NO | AO59: 18-12 se estan validando perfiles, se envio a Nacho 16-12 un perfil entrevistará CArbo en 2da fase 22-12, se ajusta a analista el 17-12, la candidatsa Raineth no cum'ple con el perfil técnico, se continua la busqueda. Se presentaron dos perfiles a Carbó Gianluca Mazzocchi y LAura ambos pasan a netrevista con Nacho, el luens 12 se envía resumen. Pasa a nueva fase con entrevistas validación tecnica con Paula Bria, con Raineth, Gianlucca, Adriel, Catriel 19-01. Pasa a preo Gianluca el martes 24-02.
A60: 00059 | B60: 46014 | C60: =IF(B60="","",IF(OR(TRIM(R60)="En curso",TRIM(R60)="En proceso de ingreso"),TODAY()-B60,"Cerrada")) -> Cerrada | D60: Ema | E60: Aprobada | J60: SANATORIO COLEGIALES | K60: CIRENDSA | L60: Hotelería | M60: Internación | N60: Servicios Generales | O60: MUCAMO/A | P60: Valeria Dodero | R60: Cerrada | S60: Ingreso | W60: Reemplazo | Y60: Monteros C | AA60: Plazo Fijo | AD60: 14-22 | AE60: SANATORIO | AF60: 46037 | AG60: 46045 | AJ60: JESICA SORIA | AK60: $1.052.963,43 bruto / $875.067,00 neto | AL60: 122/75 | AM60: NO
A61: 00060 | B61: 46017 | C61: =IF(B61="","",IF(OR(TRIM(R61)="En curso",TRIM(R61)="En proceso de ingreso"),TODAY()-B61,"Cerrada")) -> Cerrada | D61: Ema | E61: Aprobada | J61: SANATORIO COLEGIALES | K61: CIRENDSA | L61: Enfermeria | M61: Servicios de Apoyo | N61: Servicios Generales | O61: CAMILLERO/A | P61: Alvez | R61: Cerrada | S61: Ingreso | W61: Reemplazo | Y61: Busilachi J | AA61: Eventual | AD61: ROTATIVO entre los turnos 6-14 hs, 14-22 hs, 22-6 hs según cronograma | AE61: SANATORIO | AF61: 46021 | AG61: 46028 | AJ61: ALEXIS CARDOSO | AK61: $1.079.520,88 bruto / $906.107,00 neto | AL61: 122/75 | AM61: NO | AO61: 15-12 entrevista / 19-12 preo
A62: 00061 | B62: 46017 | C62: =IF(B62="","",IF(OR(TRIM(R62)="En curso",TRIM(R62)="En proceso de ingreso"),TODAY()-B62,"Cerrada")) -> Cerrada | D62: Ema | E62: Aprobada | J62: SANATORIO COLEGIALES | K62: CIRENDSA | L62: Enfermeria | M62: Servicios de Apoyo | N62: Servicios Generales | O62: CAMILLERO/A | P62: Alvez | R62: Cerrada | S62: Ingreso | W62: Reemplazo | Y62: Paz S | AA62: Plazo Fijo | AD62: 14-22 hs - 1 franco semanal a definir en el área. | AE62: SANATORIO | AF62: 46035 | AG62: 46041 | AJ62: ORTEGA JOHN | AK62: $1.195.063,16 bruto / $1.000.952,00 neto | AL62: 122/75 | AM62: NO | AO62: 16-12 entrevista / 19-12 preoc / 30-12 no apto por labo, se retoma
A63: 00062 | B63: 46017 | C63: =IF(B63="","",IF(OR(TRIM(R63)="En curso",TRIM(R63)="En proceso de ingreso"),TODAY()-B63,"Cerrada")) -> Cerrada | D63: Ema | E63: Aprobada | J63: SANATORIO COLEGIALES | K63: CIRENDSA | L63: Hotelería | M63: Internación | N63: Servicios Generales | O63: MUCAMO/A | P63: Valeria Dodero | R63: Cerrada | S63: Ingreso | W63: Reemplazo | Y63: Avellaneda Y | AA63: Plazo Fijo | AD63: 14-22 | AE63: SANATORIO | AF63: 46028 | AG63: 46041 | AJ63: JORGELINA FLORES | AK63: $1.000.154,62 BRUTO / $830.004,50 NETO | AL63: 122/75 | AM63: NO | AO63: 17-12 entrevista 23-12 preoc
A64: 00063 | B64: 46017 | C64: =IF(B64="","",IF(OR(TRIM(R64)="En curso",TRIM(R64)="En proceso de ingreso"),TODAY()-B64,"Cerrada")) -> Cerrada | D64: Ema | E64: Aprobada | J64: SANATORIO COLEGIALES | K64: CIRENDSA | L64: Admisión | M64: Consultorios Externos | N64: Administrativo/a | O64: ADMISIONISTA | P64: Gomez | R64: Cerrada | S64: Ingreso | W64: Reemplazo | Y64: Montero M | AA64: Plazo Fijo | AD64: Lunes a Viernes 14 a 20 hs, Sábado por medio 7 a 13 hs | AE64: SANATORIO | AF64: 46027 | AG64: 46034 | AJ64: AGUSTINA GIURICH | AK64: $801.551,37 bruto / $662.168,00 neto | AL64: 122/75 | AM64: NO | AO64: 17-12 entrevista 19-12 preoc
A65: 00064 | B65: 46017 | C65: =IF(B65="","",IF(OR(TRIM(R65)="En curso",TRIM(R65)="En proceso de ingreso"),TODAY()-B65,"Cerrada")) -> Cerrada | D65: Ema | E65: Aprobada | J65: SANATORIO COLEGIALES | K65: CIRENDSA | L65: Admisión | M65: Consultorios Externos | N65: Administrativo/a | O65: ADMISIONISTA | P65: Gomez | R65: Cerrada | S65: Ingreso | W65: Reemplazo | Y65: Lanza Z | AA65: Plazo Fijo | AD65: Lunes a Viernes 14 a 20 hs, Sábado por medio 7 a 13 hs | AE65: SANATORIO | AF65: 46027 | AG65: 46034 | AJ65: ROMINA RONCORONI | AK65: $801.551,37 bruto / $662.168,00 neto | AL65: 122/75 | AM65: NO | AO65: 17-12 entrevista 23-12 preoc
A66: 00065 | B66: 46017 | C66: =IF(B66="","",IF(OR(TRIM(R66)="En curso",TRIM(R66)="En proceso de ingreso"),TODAY()-B66,"Cerrada")) -> Cerrada | D66: Ema | E66: Aprobada | J66: SANATORIO COLEGIALES | K66: CIRENDSA | L66: Enfermeria | M66: Terapia Intensiva | N66: Asistencial/Enfermería | O66: Enfermero/a de Terapia Intensiva | P66: Alvez | R66: Cerrada | S66: Ingreso | W66: Reemplazo | Y66: Camino C | AA66: Eventual | AD66: 22 A 6 HS | AE66: SANATORIO | AF66: 46058 | AG66: 46062 | AJ66: EDITH LLANES | AK66: $1.554.520,85 bruto / $1.295.707,00 neto | AL66: 122/75 | AM66: NO
A67: 00066 | B67: 46017 | C67: =IF(B67="","",IF(OR(TRIM(R67)="En curso",TRIM(R67)="En proceso de ingreso"),TODAY()-B67,"Cerrada")) -> Cerrada | D67: Jose | E67: Aprobada | J67: SANATORIO COLEGIALES | L67: Sistemas | M67: Sistemas | N67: Analista IT | O67: Programador Java | P67: David | R67: Cerrada | S67: Ingreso | U67: Alta | V67: Media | W67: Reemplazo | Y67: Mantilla R | AA67: Indeterminado | AD67: L a V 09h a 18h | AE67: La Musa | AF67: 46122 | AG67: 46132 | AH67: Externa | AI67: Linkedln | AJ67: Gian Franco Stigliano | AK67: 3253012,04 bruto | AL67: FUCO | AM67: OK | AN67: NO
A68: 00067 | B68: 46019 | C68: =IF(B68="","",IF(OR(TRIM(R68)="En curso",TRIM(R68)="En proceso de ingreso"),TODAY()-B68,"Cerrada")) -> Cerrada | D68: Ema | E68: Aprobada | J68: SANATORIO COLEGIALES | K68: CIRENDSA | L68: Enfermeria | M68: Internación | N68: Asistencial/Enfermería | O68: Enfermero/a de Internación | P68: Alvez | R68: Cerrada | S68: Ingreso | U68: Baja | V68: Media | W68: Reemplazo | Y68: Aguilar M | AA68: Plazo Fijo | AD68: 14 A 22 HS | AE68: SANATORIO | AF68: 46084 | AG68: 46090 | AJ68: JOSE ROCHA | AK68: $1.223.571,44 bruto / $1.024.328,50 neto | AL68: 122/75 | AM68: NO
A69: 00068 | B69: 46020 | C69: =IF(B69="","",IF(OR(TRIM(R69)="En curso",TRIM(R69)="En proceso de ingreso"),TODAY()-B69,"Cerrada")) -> Cerrada | D69: Franco | E69: Aprobada | J69: FARMACIA | K69: Farmacia Nobel | L69: Administración | M69: Farmacia Lamaité | N69: Administrativo/a | O69: CAJERO/A | P69: Ivan Lara | R69: Cerrada | S69: Ingreso | W69: Reemplazo | Y69: Melanie Cabrera | AA69: Plazo Fijo | AD69: Lunes a Viernes 16 a 22hs y Sabados de 13 a 22hs. | AE69: Farmacia | AF69: 46030 | AG69: 46041 | AJ69: Roxana Sequeira | AK69: $1.429.794,99 bruto / $1.158.134,00 neto | AL69: 414/05 | AM69: NO | AN69: NO | AO69: 19/12 Se conocen 2 candidatos, avanza 1 a preoc.
A70: 00069 | B70: 46020 | C70: =IF(B70="","",IF(OR(TRIM(R70)="En curso",TRIM(R70)="En proceso de ingreso"),TODAY()-B70,"Cerrada")) -> Cerrada | D70: Ema | E70: Aprobada | J70: SANATORIO COLEGIALES | K70: CIRENDSA | L70: Enfermeria | M70: Terapia Intensiva | N70: Asistencial/Enfermería | O70: Enfermero/a de Terapia Intensiva | P70: Alvez | R70: Cerrada | S70: Ingreso | W70: Reemplazo | Y70: Vuelta Vasquez V a CM | AA70: Plazo Fijo | AD70: 6 A 14 HS | AE70: SANATORIO | AF70: 46063 | AG70: 46076 | AJ70: DANNA SPIRAN | AK70: $1.444.204,15 bruto / $1.205.247,26 neto | AL70: 122/75 | AM70: NO
A71: 00070 | B71: 46020 | C71: =IF(B71="","",IF(OR(TRIM(R71)="En curso",TRIM(R71)="En proceso de ingreso"),TODAY()-B71,"Cerrada")) -> Cerrada | D71: Ema | E71: Aprobada | J71: SANATORIO COLEGIALES | K71: CIRENDSA | L71: Enfermeria | M71: Terapia Intensiva | N71: Asistencial/Enfermería | O71: Enfermero/a de Terapia Intensiva | P71: Alvez | R71: Cerrada | S71: Ingreso | W71: Reemplazo | Y71: Vuelta de Placereano a CM | AA71: Plazo Fijo | AD71: 6 A 14 HS | AE71: SANATORIO | AF71: 46063 | AG71: 46076 | AJ71: JANETH VARGAS | AK71: $1.444.204,15 bruto / $1.205.247,26 neto | AL71: 122/75 | AM71: NO
A72: 00071 | B72: 46020 | C72: =IF(B72="","",IF(OR(TRIM(R72)="En curso",TRIM(R72)="En proceso de ingreso"),TODAY()-B72,"Cerrada")) -> Cerrada | D72: Ema | E72: Aprobada | J72: SANATORIO COLEGIALES | K72: CIRENDSA | L72: Hotelería | M72: Internación | N72: Servicios Generales | O72: MUCAMO/A | P72: Valeria Dodero | R72: Cerrada | S72: Ingreso | W72: Reemplazo | Y72: Menendez Ab | AA72: Plazo Fijo | AD72: 6-14 HS | AE72: SANATORIO | AF72: 46037 | AG72: 46062 | AJ72: NORMA ROJAS | AK72: $1.052.963,43 bruto / $875.067,00 neto | AL72: 122/75 | AM72: NO
A73: 00072 | B73: 46022 | C73: =IF(B73="","",IF(OR(TRIM(R73)="En curso",TRIM(R73)="En proceso de ingreso"),TODAY()-B73,"Cerrada")) -> Cerrada | D73: Franco | E73: Aprobada | J73: PREPAGA | K73: Cobensil | L73: Cobranzas | M73: Administración y Finanzas | N73: Comercial, ventas y cobranzas | O73: Cobrador/a | P73: Florencia Rodriguez | R73: Cerrada | S73: Ingreso | W73: Reemplazo | Y73: Monica Andrade (153820) | AA73: Inderminado | AD73: Lunes a Viernes de 14h a 20hs, Sabado x medio de 9 a 13hs (Part time) | AE73: Ravignani | AF73: 46028 | AG73: 46035 | AJ73: Camila Fernandez | AK73: $711.303,94 bruto / $564.434,00 neto | AL73: 130/75 | AM73: No | AN73: NO | AO73: 12/12 - Se conocen 3 candidatos, se avanzan con los 3 a preoc.
A74: 00073 | B74: 46022 | C74: =IF(B74="","",IF(OR(TRIM(R74)="En curso",TRIM(R74)="En proceso de ingreso"),TODAY()-B74,"Cerrada")) -> Cerrada | D74: Ema | E74: Aprobada | J74: SANATORIO COLEGIALES | K74: CIRENDSA | L74: Enfermeria | M74: Internación | N74: Asistencial/Enfermería | O74: Enfermero/a de Internación | P74: Alvez | R74: Cerrada | S74: Ingreso | W74: Reemplazo | Y74: Pase a TN Avircata V | AA74: Eventual | AD74: 22 A 6 HS por eventual vacaciones | AE74: SANATORIO | AF74: 46049 | AG74: 46055 | AJ74: ARIEL GUTIERREZ | AK74: $1.333.887,91 bruto / $1.114.788,00 neto | AL74: 122/75 | AM74: NO
A75: 00074 | B75: 46022 | C75: =IF(B75="","",IF(OR(TRIM(R75)="En curso",TRIM(R75)="En proceso de ingreso"),TODAY()-B75,"Cerrada")) -> Cerrada | D75: Franco | E75: Aprobada | G75: No | J75: PREPAGA | K75: Cobensil SA | L75: Ventas Retail | M75: Comercial | N75: Comercial, ventas y cobranzas | O75: VENDEDOR/A | P75: Serafin | R75: Cerrada | S75: Ingreso | W75: Reemplazo | Y75: MARTINEZ, JOEL SEBASTIAN | AA75: Inderminado | AD75: Lunes a Viernes de 10 a 18hs | AE75: Sede Colegiales (Lacroze 3257) | AF75: 46044 | AG75: 46056 | AJ75: TOROSANTUCCI, ADRIAN | AK75: $1.271.329,36 bruto / $1.036.688,00 neto | AL75: 130/75 | AM75: No | AN75: No | AO75: 03/02/26 iba a ingresar una candidata pero se bajo el dia de la firma, se retoma proceso de busqueda
A76: 00075 | B76: 46022 | C76: =IF(B76="","",IF(OR(TRIM(R76)="En curso",TRIM(R76)="En proceso de ingreso"),TODAY()-B76,"Cerrada")) -> Cerrada | D76: Franco | E76: Aprobada | J76: Centros Ambulatorios | K76: CMM | L76: Atención al Paciente | M76: Administración | N76: Administrativo/a | O76: RECEPCIONISTA | P76: Facundo De Franco | R76: Cerrada | S76: Ingreso | W76: Reemplazo | Y76: Lourdes Fiori | AA76: Inderminado | AD76: Lunes a Viernes de 11 a 20hs. | AE76: Recoleta | AF76: 46050 | AG76: 46056 | AJ76: Yanina Juarez | AK76: 1.169.193,70 bruto / $970.618,83 neto | AL76: 108/75 | AM76: No | AN76: No | AO76: 23-01 - entrrevista gestor + una candidata backup en preocupacional
A77: 00076 | B77: 46023 | C77: =IF(B77="","",IF(OR(TRIM(R77)="En curso",TRIM(R77)="En proceso de ingreso"),TODAY()-B77,"Cerrada")) -> Cerrada | D77: Ema | E77: Aprobada | J77: SANATORIO COLEGIALES | K77: CIRENDSA | L77: Hotelería | M77: Internación | N77: Servicios Generales | O77: MUCAMO/A | P77: Valeria Dodero | R77: Cerrada | S77: Ingreso | W77: Reemplazo | Y77: 1+ Vacaciones TM | AA77: Eventual | AD77: 6-14 HS | AE77: SANATORIO | AF77: 46037 | AG77: 46045 | AJ77: WILMA ROJAS | AK77: $1.052.963,43 bruto / $875.067,00 neto | AL77: 122/75 | AM77: NO | AN77: No
A78: 00077 | B78: 46023 | C78: =IF(B78="","",IF(OR(TRIM(R78)="En curso",TRIM(R78)="En proceso de ingreso"),TODAY()-B78,"Cerrada")) -> Cerrada | D78: Ema | E78: Aprobada | J78: SANATORIO COLEGIALES | K78: CIRENDSA | L78: Cirugía | M78: Quirófano | N78: Asistencial/Otros | O78: INSTRUMENTADOR/A | P78: Di Franco | R78: Cerrada | S78: Ingreso | W78: Reemplazo | Y78: Vacaciones | AA78: Eventual | AD78: Lunes a Sábados 7 a 15 hs. Feriados rotativos. | AE78: SANATORIO | AF78: 46027 | AG78: 46034 | AJ78: CATARINA RENDE | AK78: $1.478.071,38 bruto / $1.230.851,50 neto | AL78: 122/75 | AM78: NO
A79: 00078 | B79: 46023 | C79: =IF(B79="","",IF(OR(TRIM(R79)="En curso",TRIM(R79)="En proceso de ingreso"),TODAY()-B79,"Cerrada")) -> Cerrada | D79: Ema | E79: Aprobada | J79: SANATORIO COLEGIALES | K79: CIRENDSA | L79: Cirugía | M79: Quirófano | N79: Asistencial/Otros | O79: INSTRUMENTADOR/A | P79: Di Franco | R79: Cerrada | S79: Ingreso | W79: Reemplazo | Y79: Vacaciones | AA79: Eventual | AD79: Lunes a Sábados 7 a 15 hs. Feriados rotativos. | AE79: SANATORIO | AF79: 46027 | AG79: 46034 | AJ79: MELANY GUTIERREZ | AK79: $1.478.071,38 bruto / $1.230.851,50 neto | AL79: 122/75 | AM79: NO | AO79: 23/12 entrevista RRHH + Gestor 26/12 preoc 07/01 Se baja del proceso 9/1 entrevista
A80: 00079 | B80: 46023 | C80: =IF(B80="","",IF(OR(TRIM(R80)="En curso",TRIM(R80)="En proceso de ingreso"),TODAY()-B80,"Cerrada")) -> Cerrada | D80: Ema | E80: Aprobada | J80: SANATORIO COLEGIALES | K80: CIRENDSA | L80: Cirugía | M80: Quirófano | N80: Asistencial/Otros | O80: INSTRUMENTADOR/A | P80: Di Franco | R80: Cerrada | S80: Ingreso | W80: Reemplazo | Y80: Vacaciones | AA80: Eventual | AD80: Lunes a Sábados 15 a 23 hs. Feriados rotativos. | AE80: SANATORIO | AF80: 46027 | AG80: 46041 | AJ80: DOLORES VARGAS | AK80: $1.478.071,38 bruto / $1.230.851,50 neto | AL80: 122/75 | AM80: NO | AO80: 9/1 entrevista RRHH + Gestor
A81: 00080 | B81: 46023 | C81: =IF(B81="","",IF(OR(TRIM(R81)="En curso",TRIM(R81)="En proceso de ingreso"),TODAY()-B81,"Cerrada")) -> Cerrada | D81: Ema | E81: Aprobada | J81: SANATORIO COLEGIALES | K81: CIRENDSA | L81: Cirugía | M81: Quirófano | N81: Asistencial/Otros | O81: INSTRUMENTADOR/A | P81: Di Franco | R81: Cerrada | S81: Ingreso | W81: Reemplazo | Y81: Vacaciones | AA81: Eventual | AD81: L A S 15 A 23 HS. FERIADO ROTATIVO | AE81: SANATORIO | AF81: 46058 | AG81: 46062 | AJ81: ALEJANDRO CANDADO | AL81: 122/75 | AM81: NO | AO81: 23/12 entrevista RRHH 26/12 No asiste a entrevista con Gestor
A82: 00081 | B82: 46023 | C82: =IF(B82="","",IF(OR(TRIM(R82)="En curso",TRIM(R82)="En proceso de ingreso"),TODAY()-B82,"Cerrada")) -> Cerrada | D82: Ema | E82: Aprobada | J82: SANATORIO COLEGIALES | K82: CIRENDSA | L82: Enfermeria | M82: Terapia Intensiva | N82: Asistencial/Enfermería | O82: Enfermero/a de Terapia Intensiva | P82: Alvez | R82: Cerrada | S82: Ingreso | W82: Reemplazo | Y82: Vacante TM | AA82: Plazo Fijo | AD82: 6 A 14 HS | AE82: SANATORIO | AF82: 46072 | AG82: 46076 | AJ82: SANDRA DAVILA | AK82: $1.444.204,15 bruto / $1.205.247,26 neto | AL82: 122/75 | AM82: NO
A83: 00082 | B83: 46023 | C83: =IF(B83="","",IF(OR(TRIM(R83)="En curso",TRIM(R83)="En proceso de ingreso"),TODAY()-B83,"Cerrada")) -> Cerrada | D83: Ema | E83: Aprobada | J83: SANATORIO COLEGIALES | K83: CIRENDSA | L83: Enfermeria | M83: Terapia Intensiva | N83: Asistencial/Enfermería | O83: Enfermero/a de Terapia Intensiva | P83: Alvez | R83: Cerrada | S83: Ingreso | W83: Reemplazo | Y83: Vacante TM | AA83: Plazo Fijo | AD83: 6 A 14 HS | AE83: SANATORIO | AF83: 46072 | AG83: 46076 | AJ83: SERGIO MARINERO | AK83: $1.444.204,15 bruto / $1.205.247,26 neto | AL83: 122/75 | AM83: NO
A84: 00083 | B84: 46023 | C84: =IF(B84="","",IF(OR(TRIM(R84)="En curso",TRIM(R84)="En proceso de ingreso"),TODAY()-B84,"Cerrada")) -> Cerrada | D84: Ema | E84: Aprobada | J84: SANATORIO COLEGIALES | K84: CIRENDSA | L84: Enfermeria | M84: Internación | N84: Asistencial/Enfermería | O84: Enfermero/a de Internación | P84: Alvez | R84: Cerrada | S84: Ingreso | W84: Reemplazo | Y84: 1+ Vacaciones CM TM | AA84: Eventual | AD84: 6 A 14 HS por EVENTUAL vacaciones | AE84: SANATORIO | AF84: 46037 | AG84: 46055 | AJ84: ANA CESPEDES | AK84: $1.223.571,44 bruto / $1.024.328,50 neto | AL84: 122/75 | AM84: NO
A85: 00084 | B85: 46023 | C85: =IF(B85="","",IF(OR(TRIM(R85)="En curso",TRIM(R85)="En proceso de ingreso"),TODAY()-B85,"Cerrada")) -> Cerrada | D85: Ema | E85: Aprobada | J85: SANATORIO COLEGIALES | K85: CIRENDSA | L85: Enfermeria | M85: Internación | N85: Asistencial/Enfermería | O85: Enfermero/a de Internación | P85: Alvez | R85: Cerrada | S85: Ingreso | W85: Reemplazo | Y85: 1+ Vacaciones CM TN | AA85: Eventual | AD85: 22 a 6 HS por EVENTUAL vacaciones | AE85: SANATORIO | AF85: 46050 | AG85: 46055 | AJ85: KELLY CARRASCO | AK85: $1.333.887,91 bruto / $1.114.788,00 neto | AL85: 122/75 | AM85: NO
A86: 00085 | B86: 46023 | C86: =IF(B86="","",IF(OR(TRIM(R86)="En curso",TRIM(R86)="En proceso de ingreso"),TODAY()-B86,"Cerrada")) -> Cerrada | D86: Ema | E86: Aprobada | J86: SANATORIO COLEGIALES | K86: CIRENDSA | L86: Enfermeria | M86: Área Cerrada | N86: Asistencial/Enfermería | O86: Enfermero/a de área cerrada (UCO/UTI) | P86: Noelia Alvez | R86: Cerrada | S86: Ingreso | W86: Reemplazo | Y86: Tapia M | AA86: Indeterminado | AD86: TM - 6 a 14 hs | AE86: SANATORIO | AF86: 46132 | AG86: 46132 | AH86: Interna | AJ86: GUSTAVO ROCHA | AK86: Eventual. Se efectiviza el puesto | AL86: 122/75 | AM86: NO | AO86: 22/2 Preo No apto por Labo - Se retoma // 27/3 no apto por epilepsia
A87: 00086 | B87: 46024 | C87: =IF(B87="","",IF(OR(TRIM(R87)="En curso",TRIM(R87)="En proceso de ingreso"),TODAY()-B87,"Cerrada")) -> Cerrada | D87: Ema | E87: Aprobada | J87: SANATORIO COLEGIALES | K87: CIRENDSA | L87: Cirugía | M87: Quirófano | N87: Asistencial/Otros | O87: Tecnico/a de Hemodinamia | P87: Samaja | R87: Cerrada | S87: Ingreso | W87: Reemplazo | Y87: Surraco Capdevila | AA87: Inderminado | AD87: LUNES A VIERNES 17 A 22 HS. Guardias pasivas a coordinar | AE87: SANATORIO | AF87: 46043 | AG87: 46045 | AJ87: LIZ MARLENE RODRIGUEZ | AK87: $1.478.689,81 bruto / $1.233.525,50 neto | AL87: 122/75 | AM87: NO
A88: 00087 | B88: 46024 | C88: =IF(B88="","",IF(OR(TRIM(R88)="En curso",TRIM(R88)="En proceso de ingreso"),TODAY()-B88,"Cerrada")) -> Cerrada | D88: Ema | E88: Aprobada | J88: SANATORIO COLEGIALES | K88: CIRENDSA | L88: Admisión | M88: Consultorios Externos | N88: Administrativo/a | O88: ADMISIONISTA | P88: Gomez | R88: Cerrada | S88: Ingreso | W88: Reemplazo | Y88: Pase a DICOM - Colombo | AA88: Plazo Fijo | AD88: Lunes a Viernes 14 a 20 hs. Sábado por medio 7 a 13 hs | AE88: SANATORIO | AF88: 46037 | AG88: 46045 | AJ88: MARIA LAURA BLOCH | AK88: $842.805,08 bruto / $697.077,50 neto | AL88: 122/75 | AM88: NO
A89: 00088 | B89: 46024 | C89: =IF(B89="","",IF(OR(TRIM(R89)="En curso",TRIM(R89)="En proceso de ingreso"),TODAY()-B89,"Cerrada")) -> Cerrada | D89: Ema | E89: Aprobada | J89: SANATORIO COLEGIALES | K89: CIRENDSA | L89: Admisión | M89: Consultorios Externos | N89: Administrativo/a | O89: ADMISIONISTA | P89: Gomez | R89: Cerrada | S89: Ingreso | W89: Reemplazo | Y89: Pase a DICOM - Acuña | AA89: Plazo Fijo | AD89: Lunes a Viernes 14 a 20 hs. Sábado por medio 7 a 13 hs | AE89: SANATORIO | AF89: 46037 | AG89: 46045 | AJ89: LUCILA BELEN CORTES | AK89: $842.805,08 bruto / $697.077,50 neto | AL89: 122/75 | AM89: NO
A90: 00089 | B90: 46024 | C90: =IF(B90="","",IF(OR(TRIM(R90)="En curso",TRIM(R90)="En proceso de ingreso"),TODAY()-B90,"Cerrada")) -> Cerrada | D90: Ema | E90: Aprobada | J90: SANATORIO COLEGIALES | K90: CIRENDSA | L90: Hotelería | M90: Internación | N90: Servicios Generales | O90: PEON | P90: Valeria Dodero | R90: Cerrada | S90: Ingreso | W90: Reemplazo | Y90: Gutierrez M | AA90: Plazo Fijo | AD90: 22 A 6 HS. 1 franco semanal rotativo entre Sábado y Domingo. | AE90: SANATORIO | AF90: 46041 | AG90: 46045 | AJ90: FACUNDO OSORIO | AK90: $1.169.271,41 bruto / $979.802,50 neto | AL90: 122/75 | AM90: NO
A91: 00090 | B91: 46024 | C91: =IF(B91="","",IF(OR(TRIM(R91)="En curso",TRIM(R91)="En proceso de ingreso"),TODAY()-B91,"Cerrada")) -> Cerrada | D91: Ema | E91: Aprobada | J91: SANATORIO COLEGIALES | K91: CIRENDSA | L91: Hotelería | M91: Internación | N91: Servicios Generales | O91: PEON | P91: Valeria Dodero | R91: Cerrada | S91: Ingreso | W91: Reemplazo | Y91: Melillan A | AA91: Plazo Fijo | AD91: 22 A 6 HS. 1 franco semanal rotativo entre Sábado y Domingo. | AE91: SANATORIO | AF91: 46041 | AG91: 46045 | AJ91: GABRIEL PAIVA | AK91: $1.169.271,41 bruto / $979.802,50 neto | AL91: 122/75 | AM91: NO
A92: 00091 | B92: 46025 | C92: =IF(B92="","",IF(OR(TRIM(R92)="En curso",TRIM(R92)="En proceso de ingreso"),TODAY()-B92,"Cerrada")) -> Cerrada | D92: Ema | E92: Aprobada | J92: SANATORIO COLEGIALES | K92: CIRENDSA | L92: Hotelería | M92: Internación | N92: Servicios Generales | O92: MUCAMO/A | P92: Valeria Dodero | R92: Cerrada | S92: Ingreso | W92: Reemplazo | Y92: Luna E | AA92: Plazo Fijo | AD92: 14-22 HS | AE92: SANATORIO | AF92: 46028 | AG92: 46041 | AJ92: EVA MARIA PEREZ | AK92: $1.000.154,62 BRUTO / $830.004,50 NETO | AL92: 122/75 | AM92: NO
A93: 00092 | B93: 46025 | C93: =IF(B93="","",IF(OR(TRIM(R93)="En curso",TRIM(R93)="En proceso de ingreso"),TODAY()-B93,"Cerrada")) -> Cerrada | D93: Ema | E93: Aprobada | J93: SANATORIO COLEGIALES | K93: CIRENDSA | L93: Hotelería | M93: Internación | N93: Servicios Generales | O93: MUCAMO/A | P93: Valeria Dodero | R93: Cerrada | S93: Ingreso | W93: Reemplazo | Y93: Lescano C | AA93: Plazo Fijo | AD93: 14-22 HS | AE93: SANATORIO | AF93: 46037 | AG93: 46045 | AJ93: ERICA GONZALEZ | AK93: $1.052.963,43 bruto / $875.067,00 neto | AL93: 122/75 | AM93: NO | AO93: 16/1 Ant penales. Se retoma
A94: 00093 | B94: 46025 | C94: =IF(B94="","",IF(OR(TRIM(R94)="En curso",TRIM(R94)="En proceso de ingreso"),TODAY()-B94,"Cerrada")) -> Cerrada | D94: Ema | E94: Aprobada | J94: SANATORIO COLEGIALES | K94: CIRENDSA | L94: Hotelería | M94: Internación | N94: Servicios Generales | O94: MUCAMO/A | P94: Valeria Dodero | R94: Cerrada | S94: Ingreso | W94: Reemplazo | Y94: Sainz Y | AA94: Plazo Fijo | AD94: 14-22 HS | AE94: SANATORIO | AF94: 46028 | AG94: 46041 | AJ94: ALDANA AGUIRRE | AK94: $1.000.154,62 BRUTO / $830.004,50 NETO | AL94: 122/75 | AM94: NO
A95: 00094 | B95: 46027 | C95: =IF(B95="","",IF(OR(TRIM(R95)="En curso",TRIM(R95)="En proceso de ingreso"),TODAY()-B95,"Cerrada")) -> Cerrada | D95: Franco | E95: Aprobada | J95: CMV | K95: CMV | L95: Sistemas | M95: Sistemas | N95: Analista IT | O95: Soporte Tecnico | P95: Marcelo Engel | R95: Cerrada | S95: Ingreso | U95: Baja | V95: Media | W95: Reemplazo | Y95: Pablo Cammi | AA95: Inderminado | AD95: Lunes a Viernes de 13 a 21hs y Sábado por medio de 8 a 13hs (45hs semanales) | AE95: Vilella | AF95: 46077 | AG95: 46090 | AH95: Externa | AJ95: Santiago Lloveras | AK95: $1.504.151,39 bruto / 1.229.258,00 neto | AL95: 130/75 | AM95: NO | AN95: No | AO95: 4 candidatos enviados a Marcelo . Marcelo va evaluar la posibilidad de mejorar la propuesta economica ya que el horario es complejo. Entrevista con candidato por parte de rrh el 27-01-26. 29-01 entrevista con Engel. Se avanza a preoc
A96: 00095 | B96: 46027 | C96: =IF(B96="","",IF(OR(TRIM(R96)="En curso",TRIM(R96)="En proceso de ingreso"),TODAY()-B96,"Cerrada")) -> Cerrada | D96: Ema | E96: Aprobada | J96: SANATORIO COLEGIALES | K96: CIRENDSA | L96: Admisión | M96: Consultorios Externos | N96: Administrativo/a | O96: ADMISIONISTA | P96: Gomez | R96: Cerrada | S96: Ingreso | W96: Reemplazo | Y96: Molina J | AA96: Plazo Fijo | AD96: Lunes a Viernes 14 a 20 hs. Sábado por medio 7 a 13 hs | AE96: SANATORIO | AF96: 46037 | AG96: 46045 | AJ96: MARIA BELEN CAVALLERO | AK96: $842.805,08 bruto / $697.077,50 neto | AL96: 122/75 | AM96: NO
A97: 00096 | B97: 46028 | C97: =IF(B97="","",IF(OR(TRIM(R97)="En curso",TRIM(R97)="En proceso de ingreso"),TODAY()-B97,"Cerrada")) -> Cerrada | D97: Ema | E97: Aprobada | J97: CORPO | K97: HEALTHNES | L97: Contact Center | M97: Operaciones | N97: Administrativo/a | O97: Operador call center | P97: Aste | R97: Cerrada | S97: Ingreso | W97: Reemplazo | Y97: Muñoz M | AA97: Plazo Fijo | AD97: Lunes a Viernes 13 a 18 hs. Sábados 9 a 14 hs (25 hs) | AE97: CONTACT CENTER | AF97: 46063 | AG97: 46076 | AJ97: NICOLE ALMARAZ | AK97: $710.649,96 bruto / $567.231,00 neto | AL97: 130/75 | AM97: NO
A98: 00097 | B98: 46029 | C98: =IF(B98="","",IF(OR(TRIM(R98)="En curso",TRIM(R98)="En proceso de ingreso"),TODAY()-B98,"Cerrada")) -> Cerrada | D98: Franco | E98: Aprobada | G98: No | J98: PREPAGA | K98: Cobensil SA | L98: Ventas Retail | M98: Comercial | N98: Comercial, ventas y cobranzas | O98: VENDEDOR/A | P98: Serafin | R98: Cerrada | S98: Ingreso | W98: Reemplazo | Y98: PUPPO, MARIA ALICIA | AA98: Inderminado | AD98: Lunes a Viernes de 10 a 18hs | AE98: Sede de Vicente Lopez (Av. Maipu 1680) | AF98: 46044 | AG98: 46056 | AJ98: Aimar Thais Navas | AK98: $1.271.329,36 bruto / $1.036.688,00 neto | AL98: 130/75 | AM98: No | AN98: No
A99: 00098 | B99: 46029 | C99: =IF(B99="","",IF(OR(TRIM(R99)="En curso",TRIM(R99)="En proceso de ingreso"),TODAY()-B99,"Cerrada")) -> Cerrada | D99: Franco | E99: Aprobada | G99: No | J99: PREPAGA | K99: Cobensil SA | L99: Ventas Retail | M99: Comercial | N99: Comercial, ventas y cobranzas | O99: VENDEDOR/A | P99: Serafin | R99: Cerrada | S99: Ingreso | W99: Reemplazo | Y99: WARIDEL, MOIRA BELEN | AA99: Inderminado | AD99: Lunes a Viernes de 10 a 18hs | AE99: Sede Colegiales (Lacroze 3257) | AF99: 46057 | AG99: 46063 | AJ99: MEABE BRANDA, MARIA PAULA | AK99: $1.271.329,36 bruto / $1.036.688,00 neto | AL99: 130/75 | AM99: No | AN99: No | AO99: 03/02/26 iba a ingresar una candidata pero se bajo el dia de la firma, se retoma proceso de busqueda
A100: 00099 | B100: 46029 | C100: =IF(B100="","",IF(OR(TRIM(R100)="En curso",TRIM(R100)="En proceso de ingreso"),TODAY()-B100,"Cerrada")) -> Cerrada | D100: Ema | E100: Aprobada | J100: SANATORIO COLEGIALES | K100: CIRENDSA | L100: Enfermeria | M100: Internación | N100: Asistencial/Enfermería | O100: Enfermero/a de Internación | P100: Alvez | R100: Cerrada | S100: Ingreso | W100: Reemplazo | Y100: HERVAS N | AA100: Eventual | AD100: 22 A 6 HS eventual vacaciones | AE100: SANATORIO | AF100: 46049 | AG100: 46055 | AJ100: DAIANA LUCERO DIAZ | AK100: $1.333.887,91 bruto / $1.114.788,00 neto | AL100: 122/75 | AM100: NO
...

Sheet TD
A1: Unidad de Negocio | B1: (Varios elementos)
A2: Status del proceso | B2: (Todas)
A3: Status general | B3: (Varios elementos)
A5: Cuenta de Familia de Puesto
A6: 73
A10: Status general | B10: (Varios elementos)
A12: Cuenta de Familia de Puesto | B12: Status del proceso
A13: Unidad de Negocio | B13: Relevamiento de Perfil | C13: Publicación/Analizando CVs | D13: Entrevista Atracción de Talento | E13: Preocupacional | F13: Preselección/Screening | G13: Carta Oferta | H13: Entrevista Hiring Manager | I13: Assessment Center | J13: Total general
A14: SANATORIO COLEGIALES | B14: 3 | D14: 6 | E14: 7 | F14: 3 | G14: 9 | I14: 7 | J14: 35
A15: PREPAGA | D15: 3 | E15: 12 | F15: 6 | H15: 1 | J15: 22
A16: CORPO | D16: 2 | E16: 1 | H16: 5 | J16: 8
A17: CMV | C17: 1 | D17: 3 | I17: 2 | J17: 6
A18: FARMACIA | B18: 1 | F18: 1 | J18: 2
A19: Total general | B19: 4 | C19: 1 | D19: 14 | E19: 20 | F19: 10 | G19: 9 | H19: 6 | I19: 9 | J19: 73
A23: Status del proceso | B23: (Varios elementos)
A24: Status general | B24: (Varios elementos)
A26: Unidad de Negocio | B26: Cuenta de Familia de Puesto
A27: SANATORIO COLEGIALES | B27: 28
A28: PREPAGA | B28: 22
A29: CORPO | B29: 8
A30: CMV | B30: 4
A31: FARMACIA | B31: 2
A32: Total general | B32: 64
A37: Status del proceso | B37: (Todas)
A39: Cuenta de Familia de Puesto | B39: Status general
A40: Selector | B40: En curso | C40: En proceso de Ingreso | D40: Total general
A41: Ema | B41: 22 | C41: 13 | D41: 35
A42: Franco | B42: 13 | C42: 13 | D42: 26
A43: Jose | B43: 7 | C43: 4 | D43: 11
A44: Juanpi | B44: 7 | C44: 1 | D44: 8
A45: Total general | B45: 49 | C45: 31 | D45: 80
A48: Status del proceso | B48: (Todas)
A49: Unidad de Negocio | B49: (Todas)
A51: Cuenta de Familia de Puesto | B51: Status general
A52: Familia de Puesto | B52: En curso | C52: En proceso de Ingreso | D52: Total general
A53: Comercial, ventas y cobranzas | B53: 8 | C53: 12 | D53: 20
A54: Asistencial/Enfermería | B54: 13 | C54: 6 | D54: 19
A55: Liderazgo | B55: 7 | C55: 1 | D55: 8
A56: Servicios Generales | B56: 4 | C56: 4 | D56: 8
A57: Asistencial/Otros | B57: 4 | C57: 4 | D57: 8
A58: Administrativo/a | B58: 4 | D58: 4
A59: Analista | B59: 2 | C59: 1 | D59: 3
A60: Mantenimiento y obras | B60: 2 | C60: 1 | D60: 3
A61: Asistencial/Médicos | B61: 1 | C61: 2 | D61: 3
A62: Analista IT | B62: 2 | D62: 2
A63: Especialista | B63: 2 | D63: 2
A64: Total general | B64: 49 | C64: 31 | D64: 80

Sheet Referencias
A1: Selector | B1: Unidad | C1: Razon Social | D1: Sector | E1: CECO | F1: Familia de Puestos | G1: Puesto | H1: Status del Proceso | I1: Dificultad | J1: Prioridad | K1: Tipo de Vacante | L1: Motivo de contración | M1: Modalidad de contración | N1: Lugar de trabajo | O1: Fuente de selección | P1: Status General | Q1: Estado de Aprobación
A2: Franco | B2: SANATORIO COLEGIALES | C2: Desarrollos en Salud SA | D2: Enfermeria | E2: INTERNACION | F2: Asistencial/Enfermería | G2: ADMINISTRATIVO/A | H2: Relevamiento de Perfil | I2: Alta | J2: Alta | K2: Apertura de puesto | L2: Desvinculación empresa | M2: Indeterminado | O2: Linkedln | P2: En curso | Q2: Pendiente
A3: Ema | B3: CMD | C3: Cirugía Endovascular SA | D3: HOTELERIA | E3: BELGRANO | F3: Asistencial/Médicos | G3: ENFERMERO/A | H3: Publicación/Analizando CVs | I3: Media | J3: Baja | K3: Reemplazo | L3: Renuncia | M3: Plazo Fijo | O3: Computrabajo | P3: En proceso de Ingreso | Q3: Aprobación Informal
A4: Jose | B4: PREPAGA | C4: Diag por imag de alta complejidad DR Deragopyan SA | D4: ADMISION | E4: ADMINISTRACION Y FINANZAS | F4: Asistencial/Otros | G4: TECNICO/A | H4: Preselección/Screening | I4: Baja | J4: Media | L4: Crecimiento del área | M4: Eventual | O4: Referidos | P4: Cerrada | Q4: Aprobada
A5: Fer | B5: CORPO | C5: Cobensil SA | D5: CLINICA MEDICA | E5: SERVICIOS DE APOYO | F5: Analista | G5: MEDICO/A | H5: Assessment Center | I5: N/A | J5: N/A | L5: Jubilación | O5: Base general | P5: StandBy | Q5: Rechazada
A6: Juanpi | B6: CMV | C6: Healthnes SA | D6: CONTACT CENTER | E6: TERAPIA INTENSIVA | F6: Administrativo/a | G6: MUCAMO/A | H6: Entrevista Atracción de Talento | L6: Nuevo proyecto | O6: Búsqueda Interna | P6: Cancelada | Q6: Cancelada
A7: Dani | B7: DROGUERÍA | C7: Diagnostico por imágenes Pilar SA | D7: CIRUGIA | E7: Operaciones | F7: Especialista | G7: VENDEDOR/A | H7: Entrevista Hiring Manager | L7: Reorganización del área | O7: Promoción | P7: Pendiente de Aprobación
B8: ARGIL | C8: Bristol Medicine SRL | D8: Ventas Retail | E8: Comercial | F8: Servicios Generales | G8: Operador/a | H8: Preocupacional | L8: Movimiento interno | O8: Consultora
B9: FARMACIA | C9: Centrol Médico Vilella SA | D9: MKT CCENTER | E9: PILAR | F9: Mantenimiento y obras | G9: ADMIN.OPER.DE CALL CENTE | H9: Psicotécnico | L9: Licencia
B10: LABBO | C10: Reinsal SA | D10: Cobranzas | E10: Quirofano | F10: Comercial, ventas y cobranzas | G10: JEFE/A | H10: Evaluación técnica | L10: Sobre cápita
B11: SERVICIOS DE ADMINISTRACIÓN | C11: Medical S Org | D11: SUCURSALES-RECEPCION | E11: CABALLITO | F11: Analista IT | G11: ANALISTA | H11: Negociando condiciones | L11: Futura desvinculación
C12: CEMEPRO | D12: TERAPISTAS INTENSIVOS | E12: GUARDIA | F12: Pasante/Becario | G12: INSTRUMENTADOR/A | H12: Carta Oferta
C13: ARGIL SRL | D13: RADIOLOGIA | E13: Imagenes | F13: Liderazgo | G13: ADMIN.OPER.DE RECEPCION | H13: Ingreso
C14: GENESEN SA | D14: Comercial | E14: CONSULTORIOS EXTERNOS | G14: SUPERVISOR/A | H14: StandBy
C15: Farmacia Nobel SA | D15: Atencion al socio | E15: Atencion al socio | G15: COORDINADOR/A | H15: Cancelada
C16: Programa de Salud SA | D16: SUCURSALES-RECEPCION PILAR | E16: FACTURACION Y COBRANZAS | G16: RECEPCIONISTA | H16: Relevamiento de Perfil
C17: Traumato SA | D17: Mantenimiento | E17: Marketing | G17: AYUDANTE | H17: Pendiente de Aprobación
C18: Medin SA | D18: LABORATORIO | E18: Servicio de Apoyo | G18: OFICIAL
C19: Centrol Médico de la Mujer SA | D19: CARDIOLOGIA | E19: Gerencia Medica | G19: OPERARIO/A
C20: Laboratorio Internacional SA | D20: GESTION DE PERSONAS | E20: UNIDAD CORONARIA | G20: BECARIA/O
C21: Centrol Integral de Resonancia SA | D21: TRAUMATOLOGIA | E21: Administración y Finanzas | G21: PEON
D22: Sistemas | E22: FUCOS | G22: RESIDENTE 1*
D23: At. al Paciente | E23: FARMACIA LAMAITE | G23: FACTURISTA
D24: BECARIOS | E24: ARGIL | G24: Cobrador/a
D25: PRESTACIONES MEDICAS | E25: Facturación y Cobranzas | G25: Liquidador/a
D26: ADMINISTRACION Y FINANZAS | E26: DEFAULT | G26: CAMILLERO/A
D27: MEDICA- LABORATORIO | E27: QUILMES | G27: GERENTE/A
D28: SERVICIO DE ALIMENTACION | E28: Default Contable | G28: RESIDENTE 2*
D29: Maestranza | E29: Administracion | G29: ENCARGADO/A
D30: MEDICA CARDIO 2 | E30: Contact Center | G30: RESIDENTE 4*
D31: CAMILLEROS | E31: BMI | G31: RESIDENTE 3*
D32: SUCURSALES-RECEPCION LABORATORIO | E32: Contrataciones | G32: AUXILIAR
D33: Compras | E33: SAN ISIDRO | G33: EMPLEADO/A DE MOSTRADOR
... D48: Performance | E48: Laboratorio | G48: ADMIN.DE COMP. Y EE
D49: DIRECCION GENERAL | G49: ADMISIONISTA
D50: MEDICA RM1 | G50: INSTRUCTOR/A
D51: VENTAS OS.P.P | G51: COCINERO/A
D52: FIDELIZACION Y BAJAS | G52: JEFE/A DE RESIDENTES
D53: Pagos | G53: DIRECTOR/A TECNICO/A
D54: MEDICA RM3 | G54: ANALISTA DE FINANZAS
D55: COMUNICACION | G55: Soporte Tecnico
D56: DEPOSITO | G56: PROGRAMADOR/A
D57: VENTAS CORPORATIVAS | G57: ARQUITECTO/A
D58: OBRAS | G58: ABOGADO/A
D59: FINANZAS | G59: Busines Manager
D60: MEDICA RX2 | G60: DIRECTOR RESIDENCIA
... D155: Atención al Paciente | G155: Analista de Onboarding
G156: Jefe de Ventas
G157: Supervisor/a de facturación y cobranzas
G158: Responsable de Ventas Institucionales
G159: Supervisor/a de Farmacia
G160: Coordinador/a de Contac Center
G161: Coordinador/a de atracción de talento
G162: Administrativo/a comercial
G163: Liquidador/a de sueldos
G164: Pasante
G165: Administrativa/o de Laboratorio
G166: Técnico de prácticas Cardiológicas
G167: Referente de Instrumentación
... G170: EMPLEADO/A DE MOSTRADOR

Sheet Estructura del archivo
A1: Identificación de la vacante | B1: Aprobación y confidencialidad | C1: Información organizacional | D1: Información del puesto | E1: Seguimiento del proceso | F1: Tipo de necesidad | G1: Condiciones del puesto | H1: Cierre del proceso | I1: Recursos asignados | J1: Observaciones
A2: N° Vacante | B2: Estado de aprobación | C2: Unidad de Negocio | D2: Familia de Puesto | E2: Status general | F2: Tipo de vacante | G2: Modalidad de contratación | H2: Fecha de cierre | I2: Notebook | J2: Comentarios
A3: Fecha de solicitud | B3: Confidencial | C3: Razón Social | D3: Puesto | E3: Status del proceso | F3: Nombre de reemplazo | G3: Horario | H3: Fecha de ingreso
A4: Días de apertura | B4: Vacante sujeta a futura desvinculación | C4: Sector | D4: Líder | E4: Fecha estimada de ingreso | F4: Motivo de contratación | G4: Lugar de trabajo | H4: Tipo de búsqueda
A5: Selector | B5: Fecha estimada de desvinculación | C5: Centro de Costo | D5: Hiring Manager | E5: Dificultad | G5: CCT | H5: Fuente de selección
E6: Prioridad | H6: Nombre del seleccionado/a
H7: Remuneración acordada
H8: Blue

Sheet Búsqueda rápida. 
A1: Nombre del seleccionado/a: | B1: MAIA ZANE | C1: Seleccionar y/o escribir el nombre del candidato a buscar
A2: Fecha de Ingreso | B2: =_xlfn.XLOOKUP($B$1,BASE!$AJ:$AJ,BASE!$AG:$AG,"No encontrado",0) -> 46146 | C2: Si arroja como resultado "0" y/o "No encontrado" significa que el dato buscado, no se encuentra cargado en la hoja "BASE"
A3: Puesto | B3: =_xlfn.XLOOKUP($B$1,BASE!$AJ:$AJ,BASE!$O:$O,"No encontrado",0) -> TECNICO/A
A4: Sector | B4: =_xlfn.XLOOKUP($B$1,BASE!$AJ:$AJ,BASE!$L:$L,"No encontrado",0) -> LABORATORIO
A5: Centro de Costo | B5: =_xlfn.XLOOKUP($B$1,BASE!$AJ:$AJ,BASE!$M:$M,"No encontrado",0) -> INTERNACION
A6: Remuneración acordada | B6: =_xlfn.XLOOKUP($B$1,BASE!$AJ:$AJ,BASE!$AK:$AK,"No encontrado",0) -> $1.615.215,71 bruto / $1.098.029,50 neto
A7: Horario | B7: =_xlfn.XLOOKUP($B$1,BASE!$AJ:$AJ,BASE!$AD:$AD,"No encontrado",0) -> Lunes a Sábados 14 a 22 hs
A8: CCT | B8: =_xlfn.XLOOKUP($B$1,BASE!$AJ:$AJ,BASE!$AL:$AL,"No encontrado",0) -> 122/75
A9: Modalidad de contratación | B9: =_xlfn.XLOOKUP($B$1,BASE!$AJ:$AJ,BASE!$AA:$AA,"No encontrado",0) -> Inderminado
A10: Lugar de trabajo | B10: =_xlfn.XLOOKUP($B$1,BASE!$AJ:$AJ,BASE!$AE:$AE,"No encontrado",0) -> Sanatorio
A11: Líder | B11: =_xlfn.XLOOKUP($B$1,BASE!$AJ:$AJ,BASE!$P:$P,"No encontrado",0) -> Scarcelli
A12: N° Legajo reemplazo | B12: =_xlfn.XLOOKUP($B$1,BASE!$AJ:$AJ,BASE!$X:$X,"No encontrado",0) -> 0
A13: Nombre reemplazo | B13: =_xlfn.XLOOKUP($B$1,BASE!$AJ:$AJ,BASE!$Y:$Y,"No encontrado",0) -> Violeta Chinski
A14: Selector | B14: =_xlfn.XLOOKUP($B$1,BASE!$AJ:$AJ,BASE!$D:$D,"No encontrado",0) -> Ema
A15: Tipo de vacante | B15: =_xlfn.XLOOKUP($B$1,BASE!$AJ:$AJ,BASE!$W:$W,"No encontrado",0) -> Reemplazo
A16: Sector | B16: =_xlfn.XLOOKUP($B$1,BASE!$AJ:$AJ,BASE!$L:$L,"No encontrado",0) -> LABORATORIO
A17: CC. | B17: =_xlfn.XLOOKUP($B$1,BASE!$AJ:$AJ,BASE!$M:$M,"No encontrado",0) -> INTERNACION
